Workbook
Name All_Staff: Staff!$A$2:$A$47
Name Art_Staff: Staff!$A$12:$A$36
Name Audio_Staff: Staff!$A$45:$A$46
Name Design_Staff: Staff!$A$37:$A$44
Name Engineering_Staff: Staff!$A$2:$A$11
Name QA_Staff: Staff!$A$47:$A$47

Sheet Plan
A2: WORK STREAMS | H2: CONCEPT | AU2: PRE-PRODUCTION | CH2: PRODUCTION | IG2: RELEASE | OG2: LIVE SERVICE
H3: GATE 0 | I3: CONCEPT ~2 months Target: T0 Ideation | AU3: GATE 1 | AV3: PRE-PRODUCTION Target: T1-T2 R&D / GDD-TDD-Brief | CH3: GATE 2 | CI3: EARLY PROD | FG3: GATE 3 | FH3: MID PRO Target: T4 MVP | GT3: GATE 4 | GU3: END PRO Target: T5 Feature Complete | IG3: GATE 5 | IH3: ALPHA Target: T6 Playtest | JT3: GATE 6 | JU3: BETA Target: T6 Playtest | LG3: GATE 7 | LH3: LAUNCH Target: T6 | MT3: GATE 8 | MU3: FIRST RELEASE Target: T6-T7 | OG3: GATE 9 | OH3: LS 1 Live T7 | PT3: GATE 10 | PU3: LS 2 Live T8
A4: Epic | B4: Feature | C4: Story | D4: Team | E4: Size | F4: Current Tier | G4: Notes | I4: CEO | J4: Creative Director | K4: Head of Legal | L4: COO | M4: HR Manager | N4: Executive Producer | O4: Producer | P4: Game Producer | Q4: Tech Producer | R4: Art Producer | S4: Game Director | T4: Game Design Lead | U4: Level Design Lead | V4: Game Designer | W4: Combat Designer | X4: Level Designer | Y4: Technical Designer | Z4: Writer | AA4: Art Director | AB4: Concept Artist | AC4: UI/UX Designer | AD4: Graphic Designer | AE4: Character Artist | AF4: Environment Artist | AG4: Prop Artist | AH4: Animator | AI4: Character Rigger | AJ4: VFX Artist | AK4: Technical Artist | AL4: CTO | AM4: Tech Lead | AN4: Gameplay Developer | AO4: Full Stack Developer | AP4: Backend Developer | AQ4: Network Engineer | AR4: QA | AS4: Sound Designer | AT4: Platform Team | AV4: CEO | AW4: Creative Director | AX4: Head of Legal | AY4: COO | AZ4: HR Manager | BA4: Executive Producer | BB4: Producer | BC4: Game Producer | BD4: Tech Producer | BE4: Art Producer | BF4: Game Director | BG4: Game Design Lead | BH4: Level Design Lead | BI4: Game Designer | BJ4: Combat Designer | BK4: Level Designer | BL4: Technical Designer | BM4: Writer | BN4: Art Director | BO4: Concept Artist | BP4: UI/UX Designer | BQ4: Graphic Designer | BR4: Character Artist | BS4: Environment Artist | BT4: Prop Artist | BU4: Animator | BV4: Character Rigger | BW4: VFX Artist | BX4: Technical Artist | BY4: CTO | BZ4: Tech Lead | CA4: Gameplay Developer | CB4: Full Stack Developer | CC4: Backend Developer | CD4: Network Engineer | CE4: QA | CF4: Sound Designer | CG4: Platform Team | CI4: CEO | CK4: Creative Director | CM4: Head of Legal | CO4: COO | CQ4: HR Manager | CS4: Executive Producer | CU4: Producer | CW4: Game Producer | CY4: Tech Producer | DA4: Art Producer | DC4: Game Director | DE4: Game Design Lead | DG4: Level Design Lead | DI4: Game Designer | DK4: Combat Designer | DM4: Level Designer | DO4: Technical Designer | DQ4: Writer | DS4: Art Director | DU4: Concept Artist | DW4: UI/UX Designer | DY4: Graphic Designer | EA4: Character Artist | EC4: Environment Artist | EE4: Prop Artist | EG4: Animator | EI4: Character Rigger | EK4: VFX Artist | EM4: Technical Artist | EO4: CTO | EQ4: Tech Lead | ES4: Gameplay Developer | EU4: Full Stack Developer | EW4: Backend Developer | EY4: Network Engineer | FA4: QA | FC4: Sound Designer | FE4: Platform Team | FH4: CEO | FI4: Creative Director | FJ4: Head of Legal | FK4: COO | FL4: HR Manager | FM4: Executive Producer | FN4: Producer | FO4: Game Producer | FP4: Tech Producer | FQ4: Art Producer | FR4: Game Director | FS4: Game Design Lead | FT4: Level Design Lead | FU4: Game Designer | FV4: Combat Designer | FW4: Level Designer | FX4: Technical Designer | FY4: Writer | FZ4: Art Director | GA4: Concept Artist | GB4: UI/UX Designer | GC4: Graphic Designer | GD4: Character Artist | GE4: Environment Artist | GF4: Prop Artist | GG4: Animator | GH4: Character Rigger | GI4: VFX Artist | GJ4: Technical Artist | GK4: CTO | GL4: Tech Lead | GM4: Gameplay Developer | GN4: Full Stack Developer | GO4: Backend Developer | GP4: Network Engineer | GQ4: QA | GR4: Sound Designer | GS4: Platform Team | GU4: CEO | GV4: Creative Director | GW4: Head of Legal | GX4: COO | GY4: HR Manager | GZ4: Executive Producer | HA4: Producer | HB4: Game Producer | HC4: Tech Producer | HD4: Art Producer | HE4: Game Director | HF4: Game Design Lead | HG4: Level Design Lead | HH4: Game Designer | HI4: Combat Designer | HJ4: Level Designer | HK4: Technical Designer | HL4: Writer | HM4: Art Director | HN4: Concept Artist | HO4: UI/UX Designer | HP4: Graphic Designer | HQ4: Character Artist | HR4: Environment Artist | HS4: Prop Artist | HT4: Animator | HU4: Character Rigger | HV4: VFX Artist | HW4: Technical Artist | HX4: CTO | HY4: Tech Lead | HZ4: Gameplay Developer | IA4: Full Stack Developer | IB4: Backend Developer | IC4: Network Engineer | ID4: QA | IE4: Sound Designer | IF4: Platform Team | IH4: CEO | II4: Creative Director | IJ4: Head of Legal | IK4: COO | IL4: HR Manager | IM4: Executive Producer | IN4: Producer | IO4: Game Producer | IP4: Tech Producer | IQ4: Art Producer | IR4: Game Director | IS4: Game Design Lead | IT4: Level Design Lead | IU4: Game Designer | IV4: Combat Designer | IW4: Level Designer | IX4: Technical Designer | IY4: Writer | IZ4: Art Director | JA4: Concept Artist | JB4: UI/UX Designer | JC4: Graphic Designer | JD4: Character Artist | JE4: Environment Artist | JF4: Prop Artist | JG4: Animator | JH4: Character Rigger | JI4: VFX Artist | JJ4: Technical Artist | JK4: CTO | JL4: Tech Lead | JM4: Gameplay Developer | JN4: Full Stack Developer | JO4: Backend Developer | JP4: Network Engineer | JQ4: QA | JR4: Sound Designer | JS4: Platform Team | JU4: CEO | JV4: Creative Director | JW4: Head of Legal | JX4: COO | JY4: HR Manager | JZ4: Executive Producer | KA4: Producer | KB4: Game Producer | KC4: Tech Producer | KD4: Art Producer | KE4: Game Director | KF4: Game Design Lead | KG4: Level Design Lead | KH4: Game Designer | KI4: Combat Designer | KJ4: Level Designer | KK4: Technical Designer | KL4: Writer | KM4: Art Director | KN4: Concept Artist | KO4: UI/UX Designer | KP4: Graphic Designer | KQ4: Character Artist | KR4: Environment Artist | KS4: Prop Artist | KT4: Animator | KU4: Character Rigger | KV4: VFX Artist | KW4: Technical Artist | KX4: CTO | KY4: Tech Lead | KZ4: Gameplay Developer | LA4: Full Stack Developer | LB4: Backend Developer | LC4: Network Engineer | LD4: QA | LE4: Sound Designer | LF4: Platform Team | LH4: CEO | LI4: Creative Director | LJ4: Head of Legal | LK4: COO | LL4: HR Manager | LM4: Executive Producer | LN4: Producer | LO4: Game Producer | LP4: Tech Producer | LQ4: Art Producer | LR4: Game Director | LS4: Game Design Lead | LT4: Level Design Lead | LU4: Game Designer | LV4: Combat Designer | LW4: Level Designer | LX4: Technical Designer | LY4: Writer | LZ4: Art Director | MA4: Concept Artist | MB4: UI/UX Designer | MC4: Graphic Designer | MD4: Character Artist | ME4: Environment Artist | MF4: Prop Artist | MG4: Animator | MH4: Character Rigger | MI4: VFX Artist | MJ4: Technical Artist | MK4: CTO | ML4: Tech Lead | MM4: Gameplay Developer | MN4: Full Stack Developer | MO4: Backend Developer | MP4: Network Engineer | MQ4: QA | MR4: Sound Designer | MS4: Platform Team | MU4: CEO | MV4: Creative Director | MW4: Head of Legal | MX4: COO | MY4: HR Manager | MZ4: Executive Producer | NA4: Producer | NB4: Game Producer | NC4: Tech Producer | ND4: Art Producer | NE4: Game Director | NF4: Game Design Lead | NG4: Level Design Lead | NH4: Game Designer | NI4: Combat Designer | NJ4: Level Designer | NK4: Technical Designer | NL4: Writer | NM4: Art Director | NN4: Concept Artist | NO4: UI/UX Designer | NP4: Graphic Designer | NQ4: Character Artist | NR4: Environment Artist | NS4: Prop Artist | NT4: Animator | NU4: Character Rigger | NV4: VFX Artist | NW4: Technical Artist | NX4: CTO | NY4: Tech Lead | NZ4: Gameplay Developer | OA4: Full Stack Developer | OB4: Backend Developer | OC4: Network Engineer | OD4: QA | OE4: Sound Designer | OF4: Platform Team | OH4: CEO | OI4: Creative Director | OJ4: Head of Legal | OK4: COO | OL4: HR Manager | OM4: Executive Producer | ON4: Producer | OO4: Game Producer | OP4: Tech Producer | OQ4: Art Producer | OR4: Game Director | OS4: Game Design Lead | OT4: Level Design Lead | OU4: Game Designer | OV4: Combat Designer | OW4: Level Designer | OX4: Technical Designer | OY4: Writer | OZ4: Art Director | PA4: Concept Artist | PB4: UI/UX Designer | PC4: Graphic Designer | PD4: Character Artist | PE4: Environment Artist | PF4: Prop Artist | PG4: Animator | PH4: Character Rigger | PI4: VFX Artist | PJ4: Technical Artist | PK4: CTO | PL4: Tech Lead | PM4: Gameplay Developer | PN4: Full Stack Developer | PO4: Backend Developer | PP4: Network Engineer | PQ4: QA | PR4: Sound Designer | PS4: Platform Team | PU4: CEO | PV4: Creative Director | PW4: Head of Legal | PX4: COO | PY4: HR Manager | PZ4: Executive Producer | QA4: Producer | QB4: Game Producer | QC4: Tech Producer | QD4: Art Producer | QE4: Game Director | QF4: Game Design Lead | QG4: Level Design Lead | QH4: Game Designer | QI4: Combat Designer | QJ4: Level Designer | QK4: Technical Designer | QL4: Writer | QM4: Art Director | QN4: Concept Artist | QO4: UI/UX Designer | QP4: Graphic Designer | QQ4: Character Artist | QR4: Environment Artist | QS4: Prop Artist | QT4: Animator | QU4: Character Rigger | QV4: VFX Artist | QW4: Technical Artist | QX4: CTO | QY4: Tech Lead | QZ4: Gameplay Developer | RA4: Full Stack Developer | RB4: Backend Developer | RC4: Network Engineer | RD4: QA | RE4: Sound Designer | RF4: Platform Team
A5: Player Build
CI6: Min | CJ6: Max | CK6: Min | CL6: Max | CM6: Min | CN6: Max | CO6: Min | CP6: Max | CQ6: Min | CR6: Max | CS6: Min | CT6: Max | CU6: Min | CV6: Max | CW6: Min | CX6: Max | CY6: Min | CZ6: Max | DA6: Min | DB6: Max | DC6: Min | DD6: Max | DE6: Min | DF6: Max | DG6: Min | DH6: Max | DI6: Min | DJ6: Max | DK6: Min | DL6: Max | DM6: Min | DN6: Max | DO6: Min | DP6: Max | DQ6: Min | DR6: Max | DS6: Min | DT6: Max | DU6: Min | DV6: Max | DW6: Min | DX6: Max | DY6: Min | DZ6: Max | EA6: Min | EB6: Max | EC6: Min | ED6: Max | EE6: Min | EF6: Max | EG6: Min | EH6: Max | EI6: Min | EJ6: Max | EK6: Min | EL6: Max | EM6: Min | EN6: Max | EO6: Min | EP6: Max | EQ6: Min | ER6: Max | ES6: Min | ET6: Max | EU6: Min | EV6: Max | EW6: Min | EX6: Max | EY6: Min | EZ6: Max | FA6: Min | FB6: Max | FC6: Min | FD6: Max | FE6: Min | FF6: Max
B7: Player Progression | E7: L | F7: T1: R&D | DJ7: 7 | DX7: 3 | EL7: 2 | ET7: 20 | FD7: 2
C8: Player level up documentation | D8: Design | Game design | DI8: 1 | DJ8: 14
C9: Player level up configuration | D9: Design | Game design | DI9: 0.5 | DJ9: 15
C10: player level up integration | D10: Engineering | Gameplay Engineering
C11: Player level up UI | D11: Art | UX/UI | DW11: 2 | DX11: 3
C12: Character stats documentation | D12: Design | Game design | DI12: 5 | DJ12: 5
C13: Character stats implementation | D13: Engineering | Gameplay Engineering
C14: Character stats configuration in connection with other systems | D14: Design | Game design | DI14: 1 | DJ14: 10
C15: Character stats UI | D15: Art | UX/UI | DX15: 15
C16: Level up & Stats QA | D16: QA | QA
C17: Player level up documentation | D17: Design | Game design
C18: Player level up configuration | D18: Design | Game design
C19: player level up integration | D19: Engineering | Gameplay Engineering
C20: Earn different types of EXP depending on objective | D20: Engineering | Gameplay Engineering | ES20: 2 | ET20: 3
C21: Update player level and exp with (player data service) | D21: Engineering | Backend Engineering | EW21: 1 | EX21: 2
C22: Fetch player level and exp from (player data service) | D22: Engineering | Backend Engineering | EW22: 1 | EX22: 2
C23: Fetch and update UI for player level and exp | D23: Engineering | Gameplay Engineering | ES23: 1 | ET23: 2
C24: Player level up UI | D24: Art | UX/UI
C25: Character stats documentation | D25: Design | Game design
C26: Character stats implementation | D26: Engineering | Gameplay Engineering
C27: Increase stat when player level up | D27: Engineering | Gameplay Engineering | ES27: 3 | ET27: 4
C28: Update stats UI | D28: Engineering | Gameplay Engineering | ES28: 3 | ET28: 5
C29: Update player stats in backend (player data service) | D29: Engineering | Backend Engineering | EW29: 1 | EX29: 2
C30: fetch player stats from backend service (player data service) | D30: Engineering | Backend Engineering | EW30: 1 | EX30: 2
C31: Integrate stat system with other systems | D31: Engineering | Gameplay Engineering | ES31: 1 | ET31: 20
C32: Items give u stats | D32: Engineering | Gameplay Engineering | ES32: 3 | ET32: 5
C33: Character stats configuration in connection with other systems | D33: Design | Game design
C34: Character stats UI | D34: Art | UX/UI
C35: Level up & Stats QA | D35: QA | QA
B36: Skill System | E36: L | F36: T1: R&D | DJ36: 20 | DX36: 15 | EL36: 5 | ET36: 35 | FD36: 7
C37: Skill Tree UI Audio | D37: Audio | Audio | FC37: 7 | FD37: 8
C38: Skills in-game audio | D38: Audio | Audio | FC38: 7 | FD38: 8
C39: Skill System Documentation | D39: Design | Game design | DI39: 4 | DJ39: 15
C40: Skill System Implementation | D40: Engineering | Gameplay Engineering
C41: Skill System Configuration | D41: Design | Game design | DI41: 4 | DJ41: 5
C42: Skill System UI | D42: Art | UX/UI
C43: Skill system QA | D43: QA | QA
C44: Skill System Documentation | D44: Design | Game design
C45: Skill System Implementation | D45: Engineering | Gameplay Engineering
C46: Connect skill tree to UI | D46: Engineering | Gameplay Engineering | ES46: 4 | ET46: 6
C47: Add new abilities to skill tree | D47: Engineering | Gameplay Engineering | ES47: 2 | ET47: 4
C48: Add new weapons to skill tree | D48: Engineering | Gameplay Engineering | ES48: 1 | ET48: 2
C49: Fetech all skill trees from backend | D49: Engineering | Gameplay Engineering | ES49: 1 | ET49: 2
C50: Update all skill trees from backend | D50: Engineering | Gameplay Engineering | ES50: 1 | ET50: 2
C51: Sync all skill trees to backend, tool | D51: Engineering | Gameplay Engineering | ES51: 5 | ET51: 10
C52: Create weapon skill tree / nodes in (internal dashboard service) | D52: Engineering | Backend Engineering | EW52: 3 | EX52: 4
C53: Remove weapon skill tree / nodes in (internal dashboard service) | D53: Engineering | Backend Engineering | EW53: 1 | EX53: 2
C54: Update weapon skill tree / nodes in (internal dashboard service) | D54: Engineering | Backend Engineering | EW54: 1 | EX54: 2
C55: Fetch weapon skill tree / nodes in (internal dashboard service) | D55: Engineering | Backend Engineering | EW55: 1 | EX55: 2
C56: Create new collection for weapon skill tree (player data service) | D56: Engineering | Backend Engineering | EW56: 3 | EX56: 4
C57: Update player skill tree per weapon (player data service) | D57: Engineering | Backend Engineering | EW57: 1 | EX57: 2
C58: Fetch player skill tree per weapon (player data service) | D58: Engineering | Backend Engineering | EW58: 1 | EX58: 2
C59: endpoint to reset skill tree for weapons | D59: Engineering | Backend Engineering | EW59: 2 | EX59: 3
C60: Create frontend for skill tree in internal dashboard | D60: Engineering | Backend Engineering | EW60: 5 | EX60: 7
C61: Skill System Configuration | D61: Design | Game design
C62: Skill System UI | D62: Art | UX/UI
C63: Skill system QA | D63: QA | QA
B64: Achievements & Trophies | E64: M | F64: T1: R&D | DJ64: 7 | DX64: 5 | EF64: 5 | EL64: 3 | ET64: 35 | FD64: 2
C65: Trophies | D65: Art | Concept Art
B66: Factions / Reputation | E66: M | F66: T1: R&D
B67: FTUE | E67: M | F67: T2: GDD/TDD/Brief | DJ67: 16 | DV67: 5 | DX67: 5 | EC67: 32 | ED67: 47 | EH67: 5 | EL67: 12 | EN67: 10 | ET67: 15 | FD67: 2
C68: Tutorial Cave Layout Fixes | D68: Design | Level design | DM68: 7 | DN68: 10
C69: Tutorial cave set dressing fixes | D69: Art | Environment Art
C70: Tutorial Cave lighting | D70: Art | Environment Art
C71: Tutorial cave Ambience & SFX | D71: Audio | Audio | FC71: 5 | FD71: 7
C72: Tutorial Configuration/set up/texts | D72: Design | Game design | DI72: 2 | DJ72: 3
C73: Tutorial UI | D73: Art | UX/UI | DW73: 4 | DX73: 6
C74: Tutorial VFX | D74: Art | VFX
C75: Controls UI | D75: Art | UX/UI | DW75: 2 | DX75: 4
C76: Tutorial cave contents | D76: Design | Game design | DI76: 1 | DJ76: 2
C77: Narrative | D77: Design | Narrative | DQ77: 0.5 | DR77: 1
C78: Tutorial QA check | D78: QA | QA
C79: Tutorial Cave Layout Fixes | D79: Design | Level design
C80: Tutorial cave set dressing fixes | D80: Art | Environment Art
C81: Tutorial Cave lighting | D81: Art | Environment Art
C82: Tutorial cave Ambience & SFX | D82: Audio | Audio
C83: Tutorial Configuration/set up/texts | D83: Design | Game design
C84: Tutorial UI | D84: Art | UX/UI
C85: Controls UI | D85: Art | VFX
C86: Tutorial QA check | D86: QA | QA
C87: FTUE Cave | D87: Art | Environment Art | EC87: 32 | ED87: 32
B88: Professions | E88: L | F88: T1: R&D
C89: Component System Design | D89: Design | Game design | DI89: 2 | DJ89: 5
C90: Crafted Weapon Parts in-game Audio | D90: Audio | Audio | FC90: 5 | FD90: 5
C91: Forge Crafting Audio | D91: Audio | Audio | FC91: 3 | FD91: 5
C92: Forge Documentation | D92: Design | Game design | DI92: 3 | DJ92: 5
C93: Forge Concepts | D93: Art | Concept Art
C94: Forge Integration | D94: Engineering | Gameplay Engineering
C95: Forge UI | D95: Art | UX/UI | DW95: 5 | DX95: 10
C96: Forge VFX | D96: Art | VFX
C97: DA combination setup | D97: Art | TechArt
C98: Crafting Desk | D98: Art | Environment Art
C99: Forge Props | D99: Art | Character Art
C100: Forge QA | D100: QA | QA
C101: Fishing Integration | D101: Design | Game design | DI101: 3 | DJ101: 3
...

Sheet Staff
A1: Name | B1: Role | C1: Team | D1: Department
A2: Mustafa Sibai | B2: CTO | C2: Engineering | D2: Engineering
A3: Daniel Negri | B3: Full Stack Developer | C3: Web Development | D3: Engineering
A4: Nikos Gerontakis | B4: Full Stack Developer | C4: Web Development | D4: Engineering
A5: Samer Balushi | B5: Backend Developer | C5: Web Development | D5: Engineering
A6: Raynor D'Souza | B6: Gameplay Developer | C6: Gameplay | D6: Engineering
A7: Ilya Achmetov | B7: Gameplay Developer | C7: Gameplay | D7: Engineering
A8: Leon Huang | B8: Gameplay Developer | C8: Gameplay | D8: Engineering
A9: Ignasi Ezpeleta | B9: Gameplay Developer | C9: Gameplay | D9: Engineering
A10: Roberto | B10: Gameplay Developer | C10: Gameplay | D10: Engineering
A11: Matt | B11: Animator | C11: Gameplay | D11: Engineering
A12: David Luong | B12: Art Director | C12: Art Direction | D12: Art
... A47: Hannah Pickard | B47: QA | C47: QA | D47: QA

Sheet Roles
A1: Role | B1: Discipline | C1: Notes
A2: CEO | B2: Leadership
A3: Creative Director | B3: Leadership
A4: Head of Legal | B4: Leadership
A5: COO | B5: Leadership
A6: HR Manager | B6: Leadership
A7: Executive Producer | B7: Production
A8: Producer | B8: Production
A9: Game Producer | B9: Production
A10: Tech Producer | B10: Production
A11: Art Producer | B11: Production
A12: Game Director | B12: Design
A13: Game Design Lead | B13: Design
... A39: Platform Team | B39: Platform

Sheet Gates
A1: Gate | B1: Phase | D1: Target Tier | E1: Tier Name | F1: Notes
A2: 0 | B2: Concept | D2: T0 | E2: Ideation | F2: Y-doc, pitch, vision lock; all features captured at T0
A3: 1 | B3: Pre-production | D3: T1-T2 | E3: R&D / GDD-TDD-Brief | F3: GDD/TDD/Art briefs for all greenlit features (T2)
A4: 2 | B4: Early Prod | D4: T3 | E4: Prototype | F4: Prototype every feature; many bugs allowed (T3)
A5: 3 | B5: Mid Prod | D5: T4 | E5: MVP | F5: Full MVP scope - heaviest production gate (T4)
A6: 4 | B6: End Prod | D6: T5 | E6: Feature Complete | F6: Feature complete, polish to ship quality (T5)
A7: 5 | B7: Alpha | D7: T6 | E7: Player Tested | F7: Playtest, telemetry, balance pass; gating bugs only
A8: 6 | B8: Beta | D8: T6 | E8: Player Tested | F8: External player feedback, cert prep, content lock
A9: 7 | B9: Launch | D9: T6 | E9: Player Ready | F9: Day-0 readiness, marketing, store, support
A10: 8 | B10: First Release | D10: T6-T7 | E10: Player Ready / Expand | F10: Live monitoring, hotfixes, day-1/7/30 patches
A11: 9 | B11: LS 1 | D11: T7 | E11: Expand | F11: Expansions, new content drops, season cadence (T7)
A12: 10 | B12: LS 2 | D12: T8 | E12: Scale | F12: Optimize / scale post-load, sustain plan (T8)

Sheet Tiers
A1: Tier | B1: Name | C1: Definition
A2: T0 | B2: Ideation | C2: Idea captured, no commitment
A3: T1 | B3: R&D | C3: Research, prototyping intent, technical feasibility
A4: T2 | B4: GDD / TDD / Brief ready | C4: GDD done, TDD done, art brief done
A5: T3 | B5: Prototype | C5: Functional with no skins, can be bugged
A6: T4 | B6: MVP | C6: Limited quality, but full-featured
A7: T5 | B7: Feature Complete (at quality) | C7: Final assets, polished, no scope cuts left
A8: T6 | B8: Player Ready / Tested | C8: Playtest, alpha, beta, telemetry feedback applied
A9: T7 | B9: Expand | C9: Add to feature / content
A10: T8 | B10: Scale | C10: Productional optimization post-load

Sheet Legend
A1: Cell Color / Section | B1: Meaning
B2: Phase super-headers (row 1 of Plan)
A3: Concept | B3: Concept gate (T0 Ideation)
A4: Pre-production | B4: Pre-production gate (T1-T2)
A5: Production | B5: Early / Mid / End Prod gates (T3-T5)
A6: Release | B6: Alpha / Beta / Launch / First Release
A7: Live Service | B7: LS 1 / LS 2
A9: Discipline | B9: Role group color (row 3 of Plan)
A10: Leadership | B10: CEO, Head of Legal, Head of Finance & Ops, HR Manager
A11: Production | B11: Executive / Producer / Game / Tech / Art Producer
A12: Design | B12: Game Director, Design Leads, Designers, Writer
A13: Art | B13: Art Director, Concept, UI/UX, Character/Env/Prop, Anim, Rig, VFX, TA
A14: Engineering | B14: CTO, Tech Lead, Gameplay/Full Stack/Backend/Network
A15: QA | B15: QA
... A17: Platform | B17: Platform Team
A19: Sizing key (col C)
A20: S | B20: Small feature
A21: M | B21: Medium feature
A22: L | B22: Large feature
A24: How to use
A25: Plan sheet | B25: Fill in man-days per (feature, gate, role). Cells are blank by default.
A26: Totals row | B26: Bottom of Plan: SUMs each role column per gate.
A27: Headcount row | B27: Total PW / (gate months * 20 working days). Edit GATE_MONTHS in the script if your durations change.
A28: Summary sheet | B28: Auto-rolls up Plan totals per epic per gate.
A29: Adding rows | B29: Insert rows inside an epic block on Plan. Update Total PW SUM ranges if you extend past the current last data row.

Sheet Summary
A1: Epic | B1: Stories | C1: Game Director Min | D1: Game Director Max | E1: Game Design Lead Min | F1: Game Design Lead Max | G1: Level Design Lead Min | H1: Level Design Lead Max | I1: Game Designer Min | J1: Game Designer Max | K1: Combat Designer Min | L1: Combat Designer Max | M1: Level Designer Min | N1: Level Designer Max | O1: Technical Designer Min | P1: Technical Designer Max | Q1: Writer Min | R1: Writer Max | S1: Art Director Min | T1: Art Director Max | U1: Concept Artist Min | V1: Concept Artist Max | W1: UI/UX Designer Min | X1: UI/UX Designer Max | Y1: Graphic Designer Min | Z1: Graphic Designer Max | AA1: Character Artist Min | AB1: Character Artist Max | AC1: Environment Artist Min | AD1: Environment Artist Max | AE1: Prop Artist Min | AF1: Prop Artist Max | AG1: Animator Min | AH1: Animator Max | AI1: Character Rigger Min | AJ1: Character Rigger Max | AK1: VFX Artist Min | AL1: VFX Artist Max | AM1: Technical Artist Min | AN1: Technical Artist Max | AO1: CTO Min | AP1: CTO Max | AQ1: Tech Lead Min | AR1: Tech Lead Max | AS1: Gameplay Developer Min | AT1: Gameplay Developer Max | AU1: Full Stack Developer Min | AV1: Full Stack Developer Max | AW1: Backend Developer Min | AX1: Backend Developer Max | AY1: Network Engineer Min | AZ1: Network Engineer Max | BA1: QA Min | BB1: QA Max | BC1: Sound Designer Min | BD1: Sound Designer Max | BE1: Platform Team Min | BF1: Platform Team Max | BG1: Total Max
A2: Player Build | B2: =COUNTA(Plan!C6:C173) -> 156 | C2: =SUM(Plan!DC6:DC173) -> 0 | D2: =SUM(Plan!DD6:DD173) -> 0 | E2: =SUM(Plan!DE6:DE173) -> 0 | F2: =SUM(Plan!DF6:DF173) -> 0 | G2: =SUM(Plan!DG6:DG173) -> 0 | H2: =SUM(Plan!DH6:DH173) -> 0 | I2: =SUM(Plan!DI6:DI173) -> 35.5 | J2: =SUM(Plan!DJ6:DJ173) -> 169 | ... BF2: =SUM(Plan!FF6:FF173) -> 0 | BG2: =SUM(Plan!DD6:DD173)+SUM(Plan!DF6:DF173)+SUM(Plan!DH6:DH173)+SUM(Plan!DJ6:DJ173)+SUM(Plan!DL6:DL173)+SUM(Plan!DN6:DN173)+SUM(Plan!DP6:DP173)+SUM(Plan!DR6:DR173)+SUM(Plan!DT6:DT173)+SUM(Plan!DV6:DV173)+SUM(Plan!DX6:DX173)+SUM(Plan!DZ6:DZ173)+SUM(Plan!EB6:EB173)+SUM(Plan!ED6:ED173)+SUM(Plan!EF6:EF173)+SUM(Plan!EH6:EH173)+SUM(Plan!EJ6:EJ173)+SUM(Plan!EL6:EL173)+SUM(Plan!EN6:EN173)+SUM(Plan!EP6:EP173)+SUM(Plan!ER6:ER173)+SUM(Plan!ET6:ET173)+SUM(Plan!EV6:EV173)+SUM(Plan!EX6:EX173)+SUM(Plan!EZ6:EZ173)+SUM(Plan!FB6:FB173)+SUM(Plan!FD6:FD173)+SUM(Plan!FF6:FF173) -> 817
A3: World Systems | B3: =COUNTA(Plan!C175:C615) -> 411 | C3: =SUM(Plan!DC175:DC615) -> 0 | D3: =SUM(Plan!DD175:DD615) -> 0 | E3: =SUM(Plan!DE175:DE615) -> 0 | F3: =SUM(Plan!DF175:DF615) -> 0 | G3: =SUM(Plan!DG175:DG615) -> 0 | H3: =SUM(Plan!DH175:DH615) -> 0 | I3: =SUM(Plan!DI175:DI615) -> 74.5 | J3: =SUM(Plan!DJ175:DJ615) -> 222 | ... BF3: =SUM(Plan!FF175:FF615) -> 0 | BG3: =SUM(Plan!DD175:DD615)+SUM(Plan!DF175:DF615)+SUM(Plan!DH175:DH615)+SUM(Plan!DJ175:DJ615)+SUM(Plan!DL175:DL615)+SUM(Plan!DN175:DN615)+SUM(Plan!DP175:DP615)+SUM(Plan!DR175:DR615)+SUM(Plan!DT175:DT615)+SUM(Plan!DV175:DV615)+SUM(Plan!DX175:DX615)+SUM(Plan!DZ175:DZ615)+SUM(Plan!EB175:EB615)+SUM(Plan!ED175:ED615)+SUM(Plan!EF175:EF615)+SUM(Plan!EH175:EH615)+SUM(Plan!EJ175:EJ615)+SUM(Plan!EL175:EL615)+SUM(Plan!EN175:EN615)+SUM(Plan!EP175:EP615)+SUM(Plan!ER175:ER615)+SUM(Plan!ET175:ET615)+SUM(Plan!EV175:EV615)+SUM(Plan!EX175:EX615)+SUM(Plan!EZ175:EZ615)+SUM(Plan!FB175:FB615)+SUM(Plan!FD175:FD615)+SUM(Plan!FF175:FF615) -> 3607.6
A4: Combat | B4: =COUNTA(Plan!C617:C948) -> 322 | C4: =SUM(Plan!DC617:DC948) -> 0 | D4: =SUM(Plan!DD617:DD948) -> 5 | E4: =SUM(Plan!DE617:DE948) -> 0 | F4: =SUM(Plan!DF617:DF948) -> 0 | G4: =SUM(Plan!DG617:DG948) -> 0 | H4: =SUM(Plan!DH617:DH948) -> 0 | I4: =SUM(Plan!DI617:DI948) -> 80.5 | J4: =SUM(Plan!DJ617:DJ948) -> 277 | ... BF4: =SUM(Plan!FF617:FF948) -> 0 | BG4: =SUM(Plan!DD617:DD948)+SUM(Plan!DF617:DF948)+SUM(Plan!DH617:DH948)+SUM(Plan!DJ617:DJ948)+SUM(Plan!DL617:DL948)+SUM(Plan!DN617:DN948)+SUM(Plan!DP617:DP948)+SUM(Plan!DR617:DR948)+SUM(Plan!DT617:DT948)+SUM(Plan!DV617:DV948)+SUM(Plan!DX617:DX948)+SUM(Plan!DZ617:DZ948)+SUM(Plan!EB617:EB948)+SUM(Plan!ED617:ED948)+SUM(Plan!EF617:EF948)+SUM(Plan!EH617:EH948)+SUM(Plan!EJ617:EJ948)+SUM(Plan!EL617:EL948)+SUM(Plan!EN617:EN948)+SUM(Plan!EP617:EP948)+SUM(Plan!ER617:ER948)+SUM(Plan!ET617:ET948)+SUM(Plan!EV617:EV948)+SUM(Plan!EX617:EX948)+SUM(Plan!EZ617:EZ948)+SUM(Plan!FB617:FB948)+SUM(Plan!FD617:FD948)+SUM(Plan!FF617:FF948) -> 2030.4
A5: User Space | B5: =COUNTA(Plan!C950:C1039) -> 81 | C5: =SUM(Plan!DC950:DC1039) -> 0 | D5: =SUM(Plan!DD950:DD1039) -> 0 | E5: =SUM(Plan!DE950:DE1039) -> 0 | F5: =SUM(Plan!DF950:DF1039) -> 0 | G5: =SUM(Plan!DG950:DG1039) -> 0 | H5: =SUM(Plan!DH950:DH1039) -> 0 | I5: =SUM(Plan!DI950:DI1039) -> 5 | J5: =SUM(Plan!DJ950:DJ1039) -> 26 | ... BF5: =SUM(Plan!FF950:FF1039) -> 0 | BG5: =SUM(Plan!DD950:DD1039)+SUM(Plan!DF950:DF1039)+SUM(Plan!DH950:DH1039)+SUM(Plan!DJ950:DJ1039)+SUM(Plan!DL950:DL1039)+SUM(Plan!DN950:DN1039)+SUM(Plan!DP950:DP1039)+SUM(Plan!DR950:DR1039)+SUM(Plan!DT950:DT1039)+SUM(Plan!DV950:DV1039)+SUM(Plan!DX950:DX1039)+SUM(Plan!DZ950:DZ1039)+SUM(Plan!EB950:EB1039)+SUM(Plan!ED950:ED1039)+SUM(Plan!EF950:EF1039)+SUM(Plan!EH950:EH1039)+SUM(Plan!EJ950:EJ1039)+SUM(Plan!EL950:EL1039)+SUM(Plan!EN950:EN1039)+SUM(Plan!EP950:EP1039)+SUM(Plan!ER950:ER1039)+SUM(Plan!ET950:ET1039)+SUM(Plan!EV950:EV1039)+SUM(Plan!EX950:EX1039)+SUM(Plan!EZ950:EZ1039)+SUM(Plan!FB950:FB1039)+SUM(Plan!FD950:FD1039)+SUM(Plan!FF950:FF1039) -> 1200.4
A6: Items & Inventory | B6: =COUNTA(Plan!C1041:C1133) -> 83 | C6: =SUM(Plan!DC1041:DC1133) -> 0 | D6: =SUM(Plan!DD1041:DD1133) -> 0 | E6: =SUM(Plan!DE1041:DE1133) -> 0 | F6: =SUM(Plan!DF1041:DF1133) -> 0 | G6: =SUM(Plan!DG1041:DG1133) -> 0 | H6: =SUM(Plan!DH1041:DH1133) -> 0 | I6: =SUM(Plan!DI1041:DI1133) -> 8 | J6: =SUM(Plan!DJ1041:DJ1133) -> 47 | ... BF6: =SUM(Plan!FF1041:FF1133) -> 0 | BG6: =SUM(Plan!DD1041:DD1133)+SUM(Plan!DF1041:DF1133)+SUM(Plan!DH1041:DH1133)+SUM(Plan!DJ1041:DJ1133)+SUM(Plan!DL1041:DL1133)+SUM(Plan!DN1041:DN1133)+SUM(Plan!DP1041:DP1133)+SUM(Plan!DR1041:DR1133)+SUM(Plan!DT1041:DT1133)+SUM(Plan!DV1041:DV1133)+SUM(Plan!DX1041:DX1133)+SUM(Plan!DZ1041:DZ1133)+SUM(Plan!EB1041:EB1133)+SUM(Plan!ED1041:ED1133)+SUM(Plan!EF1041:EF1133)+SUM(Plan!EH1041:EH1133)+SUM(Plan!EJ1041:EJ1133)+SUM(Plan!EL1041:EL1133)+SUM(Plan!EN1041:EN1133)+SUM(Plan!EP1041:EP1133)+SUM(Plan!ER1041:ER1133)+SUM(Plan!ET1041:ET1133)+SUM(Plan!EV1041:EV1133)+SUM(Plan!EX1041:EX1133)+SUM(Plan!EZ1041:EZ1133)+SUM(Plan!FB1041:FB1133)+SUM(Plan!FD1041:FD1133)+SUM(Plan!FF1041:FF1133) -> 524
A7: Player Economy | B7: =COUNTA(Plan!C1135:C1215) -> 73 | C7: =SUM(Plan!DC1135:DC1215) -> 0 | D7: =SUM(Plan!DD1135:DD1215) -> 0 | E7: =SUM(Plan!DE1135:DE1215) -> 0 | F7: =SUM(Plan!DF1135:DF1215) -> 0 | G7: =SUM(Plan!DG1135:DG1215) -> 0 | H7: =SUM(Plan!DH1135:DH1215) -> 0 | I7: =SUM(Plan!DI1135:DI1215) -> 17 | J7: =SUM(Plan!DJ1135:DJ1215) -> 129 | ... BF7: =SUM(Plan!FF1135:FF1215) -> 0 | BG7: =SUM(Plan!DD1135:DD1215)+SUM(Plan!DF1135:DF1215)+SUM(Plan!DH1135:DH1215)+SUM(Plan!DJ1135:DJ1215)+SUM(Plan!DL1135:DL1215)+SUM(Plan!DN1135:DN1215)+SUM(Plan!DP1135:DP1215)+SUM(Plan!DR1135:DR1215)+SUM(Plan!DT1135:DT1215)+SUM(Plan!DV1135:DV1215)+SUM(Plan!DX1135:DX1215)+SUM(Plan!DZ1135:DZ1215)+SUM(Plan!EB1135:EB1215)+SUM(Plan!ED1135:ED1215)+SUM(Plan!EF1135:EF1215)+SUM(Plan!EH1135:EH1215)+SUM(Plan!EJ1135:EJ1215)+SUM(Plan!EL1135:EL1215)+SUM(Plan!EN1135:EN1215)+SUM(Plan!EP1135:EP1215)+SUM(Plan!ER1135:ER1215)+SUM(Plan!ET1135:ET1215)+SUM(Plan!EV1135:EV1215)+SUM(Plan!EX1135:EX1215)+SUM(Plan!EZ1135:EZ1215)+SUM(Plan!FB1135:FB1215)+SUM(Plan!FD1135:FD1215)+SUM(Plan!FF1135:FF1215) -> 794
A8: Quest System | B8: =COUNTA(Plan!C1217:C1343) -> 114 | C8: =SUM(Plan!DC1217:DC1343) -> 0 | D8: =SUM(Plan!DD1217:DD1343) -> 5 | E8: =SUM(Plan!DE1217:DE1343) -> 0 | F8: =SUM(Plan!DF1217:DF1343) -> 0 | G8: =SUM(Plan!DG1217:DG1343) -> 0 | H8: =SUM(Plan!DH1217:DH1343) -> 0 | I8: =SUM(Plan!DI1217:DI1343) -> 116 | J8: =SUM(Plan!DJ1217:DJ1343) -> 154 | ... BF8: =SUM(Plan!FF1217:FF1343) -> 0 | BG8: =SUM(Plan!DD1217:DD1343)+SUM(Plan!DF1217:DF1343)+SUM(Plan!DH1217:DH1343)+SUM(Plan!DJ1217:DJ1343)+SUM(Plan!DL1217:DL1343)+SUM(Plan!DN1217:DN1343)+SUM(Plan!DP1217:DP1343)+SUM(Plan!DR1217:DR1343)+SUM(Plan!DT1217:DT1343)+SUM(Plan!DV1217:DV1343)+SUM(Plan!DX1217:DX1343)+SUM(Plan!DZ1217:DZ1343)+SUM(Plan!EB1217:EB1343)+SUM(Plan!ED1217:ED1343)+SUM(Plan!EF1217:EF1343)+SUM(Plan!EH1217:EH1343)+SUM(Plan!EJ1217:EJ1343)+SUM(Plan!EL1217:EL1343)+SUM(Plan!EN1217:EN1343)+SUM(Plan!EP1217:EP1343)+SUM(Plan!ER1217:ER1343)+SUM(Plan!ET1217:ET1343)+SUM(Plan!EV1217:EV1343)+SUM(Plan!EX1217:EX1343)+SUM(Plan!EZ1217:EZ1343)+SUM(Plan!FB1217:FB1343)+SUM(Plan!FD1217:FD1343)+SUM(Plan!FF1217:FF1343) -> 666.5
A9: Social & Multiplayer | B9: =COUNTA(Plan!C1345:C1500) -> 145 | C9: =SUM(Plan!DC1345:DC1500) -> 0 | D9: =SUM(Plan!DD1345:DD1500) -> 5 | E9: =SUM(Plan!DE1345:DE1500) -> 0 | F9: =SUM(Plan!DF1345:DF1500) -> 0 | G9: =SUM(Plan!DG1345:DG1500) -> 0 | H9: =SUM(Plan!DH1345:DH1500) -> 0 | I9: =SUM(Plan!DI1345:DI1500) -> 3 | J9: =SUM(Plan!DJ1345:DJ1500) -> 61 | ... BF9: =SUM(Plan!FF1345:FF1500) -> 0 | BG9: =SUM(Plan!DD1345:DD1500)+SUM(Plan!DF1345:DF1500)+SUM(Plan!DH1345:DH1500)+SUM(Plan!DJ1345:DJ1500)+SUM(Plan!DL1345:DL1500)+SUM(Plan!DN1345:DN1500)+SUM(Plan!DP1345:DP1500)+SUM(Plan!DR1345:DR1500)+SUM(Plan!DT1345:DT1500)+SUM(Plan!DV1345:DV1500)+SUM(Plan!DX1345:DX1500)+SUM(Plan!DZ1345:DZ1500)+SUM(Plan!EB1345:EB1500)+SUM(Plan!ED1345:ED1500)+SUM(Plan!EF1345:EF1500)+SUM(Plan!EH1345:EH1500)+SUM(Plan!EJ1345:EJ1500)+SUM(Plan!EL1345:EL1500)+SUM(Plan!EN1345:EN1500)+SUM(Plan!EP1345:EP1500)+SUM(Plan!ER1345:ER1500)+SUM(Plan!ET1345:ET1500)+SUM(Plan!EV1345:EV1500)+SUM(Plan!EX1345:EX1500)+SUM(Plan!EZ1345:EZ1500)+SUM(Plan!FB1345:FB1500)+SUM(Plan!FD1345:FD1500)+SUM(Plan!FF1345:FF1500) -> 1283.6
A10: Game Bibles | B10: =COUNTA(Plan!C1502:C1517) -> 9 | C10: =SUM(Plan!DC1502:DC1517) -> 0 | D10: =SUM(Plan!DD1502:DD1517) -> 0 | E10: =SUM(Plan!DE1502:DE1517) -> 0 | F10: =SUM(Plan!DF1502:DF1517) -> 0 | G10: =SUM(Plan!DG1502:DG1517) -> 0 | H10: =SUM(Plan!DH1502:DH1517) -> 0 | I10: =SUM(Plan!DI1502:DI1517) -> 0 | J10: =SUM(Plan!DJ1502:DJ1517) -> 40 | ... BF10: =SUM(Plan!FF1502:FF1517) -> 0 | BG10: =SUM(Plan!DD1502:DD1517)+SUM(Plan!DF1502:DF1517)+SUM(Plan!DH1502:DH1517)+SUM(Plan!DJ1502:DJ1517)+SUM(Plan!DL1502:DL1517)+SUM(Plan!DN1502:DN1517)+SUM(Plan!DP1502:DP1517)+SUM(Plan!DR1502:DR1517)+SUM(Plan!DT1502:DT1517)+SUM(Plan!DV1502:DV1517)+SUM(Plan!DX1502:DX1517)+SUM(Plan!DZ1502:DZ1517)+SUM(Plan!EB1502:EB1517)+SUM(Plan!ED1502:ED1517)+SUM(Plan!EF1502:EF1517)+SUM(Plan!EH1502:EH1517)+SUM(Plan!EJ1502:EJ1517)+SUM(Plan!EL1502:EL1517)+SUM(Plan!EN1502:EN1517)+SUM(Plan!EP1502:EP1517)+SUM(Plan!ER1502:ER1517)+SUM(Plan!ET1502:ET1517)+SUM(Plan!EV1502:EV1517)+SUM(Plan!EX1502:EX1517)+SUM(Plan!EZ1502:EZ1517)+SUM(Plan!FB1502:FB1517)+SUM(Plan!FD1502:FD1517)+SUM(Plan!FF1502:FF1517) -> 110.1
A11: Platform | B11: =COUNTA(Plan!C1519:C1582) -> 44 | C11: =SUM(Plan!DC1519:DC1582) -> 0 | D11: =SUM(Plan!DD1519:DD1582) -> 0 | E11: =SUM(Plan!DE1519:DE1582) -> 0 | F11: =SUM(Plan!DF1519:DF1582) -> 0 | G11: =SUM(Plan!DG1519:DG1582) -> 0 | H11: =SUM(Plan!DH1519:DH1582) -> 0 | I11: =SUM(Plan!DI1519:DI1582) -> 3 | J11: =SUM(Plan!DJ1519:DJ1582) -> 5 | ... BF11: =SUM(Plan!FF1519:FF1582) -> 0 | BG11: =SUM(Plan!DD1519:DD1582)+SUM(Plan!DF1519:DF1582)+SUM(Plan!DH1519:DH1582)+SUM(Plan!DJ1519:DJ1582)+SUM(Plan!DL1519:DL1582)+SUM(Plan!DN1519:DN1582)+SUM(Plan!DP1519:DP1582)+SUM(Plan!DR1519:DR1582)+SUM(Plan!DT1519:DT1582)+SUM(Plan!DV1519:DV1582)+SUM(Plan!DX1519:DX1582)+SUM(Plan!DZ1519:DZ1582)+SUM(Plan!EB1519:EB1582)+SUM(Plan!ED1519:ED1582)+SUM(Plan!EF1519:EF1582)+SUM(Plan!EH1519:EH1582)+SUM(Plan!EJ1519:EJ1582)+SUM(Plan!EL1519:EL1582)+SUM(Plan!EN1519:EN1582)+SUM(Plan!EP1519:EP1582)+SUM(Plan!ER1519:ER1582)+SUM(Plan!ET1519:ET1582)+SUM(Plan!EV1519:EV1582)+SUM(Plan!EX1519:EX1582)+SUM(Plan!EZ1519:EZ1582)+SUM(Plan!FB1519:FB1582)+SUM(Plan!FD1519:FD1582)+SUM(Plan!FF1519:FF1582) -> 338
A12: Live Game | B12: =COUNTA(Plan!C1584:C1591) -> 0 | C12: =SUM(Plan!DC1584:DC1591) -> 0 | D12: =SUM(Plan!DD1584:DD1591) -> 0 | E12: =SUM(Plan!DE1584:DE1591) -> 0 | F12: =SUM(Plan!DF1584:DF1591) -> 0 | G12: =SUM(Plan!DG1584:DG1591) -> 0 | H12: =SUM(Plan!DH1584:DH1591) -> 0 | I12: =SUM(Plan!DI1584:DI1591) -> 0 | J12: =SUM(Plan!DJ1584:DJ1591) -> 0 | ... BF12: =SUM(Plan!FF1584:FF1591) -> 0 | BG12: =SUM(Plan!DD1584:DD1591)+SUM(Plan!DF1584:DF1591)+SUM(Plan!DH1584:DH1591)+SUM(Plan!DJ1584:DJ1591)+SUM(Plan!DL1584:DL1591)+SUM(Plan!DN1584:DN1591)+SUM(Plan!DP1584:DP1591)+SUM(Plan!DR1584:DR1591)+SUM(Plan!DT1584:DT1591)+SUM(Plan!DV1584:DV1591)+SUM(Plan!DX1584:DX1591)+SUM(Plan!DZ1584:DZ1591)+SUM(Plan!EB1584:EB1591)+SUM(Plan!ED1584:ED1591)+SUM(Plan!EF1584:EF1591)+SUM(Plan!EH1584:EH1591)+SUM(Plan!EJ1584:EJ1591)+SUM(Plan!EL1584:EL1591)+SUM(Plan!EN1584:EN1591)+SUM(Plan!EP1584:EP1591)+SUM(Plan!ER1584:ER1591)+SUM(Plan!ET1584:ET1591)+SUM(Plan!EV1584:EV1591)+SUM(Plan!EX1584:EX1591)+SUM(Plan!EZ1584:EZ1591)+SUM(Plan!FB1584:FB1591)+SUM(Plan!FD1584:FD1591)+SUM(Plan!FF1584:FF1591) -> 0
A13: Partner Build | B13: =COUNTA(Plan!C1593:C1601) -> 0 | C13: =SUM(Plan!DC1593:DC1601) -> 0 | D13: =SUM(Plan!DD1593:DD1601) -> 0 | E13: =SUM(Plan!DE1593:DE1601) -> 0 | F13: =SUM(Plan!DF1593:DF1601) -> 0 | G13: =SUM(Plan!DG1593:DG1601) -> 0 | H13: =SUM(Plan!DH1593:DH1601) -> 0 | I13: =SUM(Plan!DI1593:DI1601) -> 0 | J13: =SUM(Plan!DJ1593:DJ1601) -> 0 | ... BF13: =SUM(Plan!FF1593:FF1601) -> 0 | BG13: =SUM(Plan!DD1593:DD1601)+SUM(Plan!DF1593:DF1601)+SUM(Plan!DH1593:DH1601)+SUM(Plan!DJ1593:DJ1601)+SUM(Plan!DL1593:DL1601)+SUM(Plan!DN1593:DN1601)+SUM(Plan!DP1593:DP1601)+SUM(Plan!DR1593:DR1601)+SUM(Plan!DT1593:DT1601)+SUM(Plan!DV1593:DV1601)+SUM(Plan!DX1593:DX1601)+SUM(Plan!DZ1593:DZ1601)+SUM(Plan!EB1593:EB1601)+SUM(Plan!ED1593:ED1601)+SUM(Plan!EF1593:EF1601)+SUM(Plan!EH1593:EH1601)+SUM(Plan!EJ1593:EJ1601)+SUM(Plan!EL1593:EL1601)+SUM(Plan!EN1593:EN1601)+SUM(Plan!EP1593:EP1601)+SUM(Plan!ER1593:ER1601)+SUM(Plan!ET1593:ET1601)+SUM(Plan!EV1593:EV1601)+SUM(Plan!EX1593:EX1601)+SUM(Plan!EZ1593:EZ1601)+SUM(Plan!FB1593:FB1601)+SUM(Plan!FD1593:FD1601)+SUM(Plan!FF1593:FF1601) -> 0
A14: Product Publishing | B14: =COUNTA(Plan!C1603:C1619) -> 9 | C14: =SUM(Plan!DC1603:DC1619) -> 0 | D14: =SUM(Plan!DD1603:DD1619) -> 0 | E14: =SUM(Plan!DE1603:DE1619) -> 0 | F14: =SUM(Plan!DF1603:DF1619) -> 0 | G14: =SUM(Plan!DG1603:DG1619) -> 0 | H14: =SUM(Plan!DH1603:DH1619) -> 0 | I14: =SUM(Plan!DI1603:DI1619) -> 0 | J14: =SUM(Plan!DJ1603:DJ1619) -> 0 | ... BF14: =SUM(Plan!FF1603:FF1619) -> 0 | BG14: =SUM(Plan!DD1603:DD1619)+SUM(Plan!DF1603:DF1619)+SUM(Plan!DH1603:DH1619)+SUM(Plan!DJ1603:DJ1619)+SUM(Plan!DL1603:DL1619)+SUM(Plan!DN1603:DN1619)+SUM(Plan!DP1603:DP1619)+SUM(Plan!DR1603:DR1619)+SUM(Plan!DT1603:DT1619)+SUM(Plan!DV1603:DV1619)+SUM(Plan!DX1603:DX1619)+SUM(Plan!DZ1603:DZ1619)+SUM(Plan!EB1603:EB1619)+SUM(Plan!ED1603:ED1619)+SUM(Plan!EF1603:EF1619)+SUM(Plan!EH1603:EH1619)+SUM(Plan!EJ1603:EJ1619)+SUM(Plan!EL1603:EL1619)+SUM(Plan!EN1603:EN1619)+SUM(Plan!EP1603:EP1619)+SUM(Plan!ER1603:ER1619)+SUM(Plan!ET1603:ET1619)+SUM(Plan!EV1603:EV1619)+SUM(Plan!EX1603:EX1619)+SUM(Plan!EZ1603:EZ1619)+SUM(Plan!FB1603:FB1619)+SUM(Plan!FD1603:FD1619)+SUM(Plan!FF1603:FF1619) -> 25
A15: TOTAL | B15: =SUM(B2:B14) -> 1447 | C15: =SUM(C2:C14) -> 0 | D15: =SUM(D2:D14) -> 15 | E15: =SUM(E2:E14) -> 0 | F15: =SUM(F2:F14) -> 0 | G15: =SUM(G2:G14) -> 0 | H15: =SUM(H2:H14) -> 0 | I15: =SUM(I2:I14) -> 342.5 | ... BG15: =SUM(BG2:BG14) -> 11396.6

Sheet Epics & Features
A1: Epic | B1: Feature | C1: Sizing | D1: Current Tier | E1: Stories
A2: Player Build
B3: Player Progression | C3: L | D3: T1: R&D | E3: =COUNTIF(Plan!B:B,B3) -> 1
B4: Skill System | C4: L | D4: T1: R&D | E4: =COUNTIF(Plan!B:B,B4) -> 1
B5: Achievements & Trophies | C5: M | D5: T1: R&D | E5: =COUNTIF(Plan!B:B,B5) -> 1
B6: Factions / Reputation | C6: M | D6: T1: R&D | E6: =COUNTIF(Plan!B:B,B6) -> 1
B7: FTUE | C7: M | D7: T2: GDD/TDD/Brief | E7: =COUNTIF(Plan!B:B,B7) -> 1
B8: Professions | C8: L | D8: T1: R&D | E8: =COUNTIF(Plan!B:B,B8) -> 1
B9: Character Management | C9: M | D9: T0: Ideation | E9: =COUNTIF(Plan!B:B,B9) -> 1
B10: Character Creation & Customization | C10: L | D10: T1: R&D | E10: =COUNTIF(Plan!B:B,B10) -> 1
B11: Garment System | C11: M | D11: T0: Ideation | E11: =COUNTIF(Plan!B:B,B11) -> 1
B12: Persona System | C12: M | D12: T1: R&D | E12: =COUNTIF(Plan!B:B,B12) -> 1
B13: Emote System | C13: S | D13: T0: Ideation | E13: =COUNTIF(Plan!B:B,B13) -> 1
A14: World Systems
B15: Foam Corruption | C15: M | D15: T2: GDD/TDD/Brief | E15: =COUNTIF(Plan!B:B,B15) -> 1
B16: Miasma Corruption | C16: M | D16: T0: Ideation | E16: =COUNTIF(Plan!B:B,B16) -> 1
B17: Water Corruption | C17: M | D17: T0: Ideation | E17: =COUNTIF(Plan!B:B,B17) -> 1
B18: Crystal Corruption | C18: M | D18: T0: Ideation | E18: =COUNTIF(Plan!B:B,B18) -> 1
B19: Time Corruption | C19: M | D19: T0: Ideation | E19: =COUNTIF(Plan!B:B,B19) -> 1
B20: Enemy Corruption | C20: M | D20: T0: Ideation | E20: =COUNTIF(Plan!B:B,B20) -> 1
B21: Oil Corruption | C21: M | D21: T0: Ideation | E21: =COUNTIF(Plan!B:B,B21) -> 1
B22: Texture Corruption | C22: M | D22: T0: Ideation | E22: =COUNTIF(Plan!B:B,B22) -> 1
B23: Environmental Elemental Effects (combination states) | C23: L | D23: T2: GDD/TDD/Brief | E23: =COUNTIF(Plan!B:B,B23) -> 1
B24: Basic Movement System | C24: L | D24: T1: R&D | E24: =COUNTIF(Plan!B:B,B24) -> 1
B25: Advanced Traversal | C25: L | D25: T1: R&D | E25: =COUNTIF(Plan!B:B,B25) -> 1
B26: Navigation | C26: M | D26: T0: Ideation | E26: =COUNTIF(Plan!B:B,B26) -> 1
... B43: Biome - Downtime | C43: M | D43: T4: MVP | E43: =COUNTIF(Plan!B:B,B43) -> 1
A44: Combat
B45: Combat Framework | C45: L | D45: T2: GDD/TDD/Brief | E45: =COUNTIF(Plan!B:B,B45) -> 1
B46: Ranged Combat | C46: M | D46: T0: Ideation | E46: =COUNTIF(Plan!B:B,B46) -> 1
B47: Combat AI Behavior | C47: L | D47: T0: Ideation | E47: =COUNTIF(Plan!B:B,B47) -> 1
B48: Enemies Art | C48: M | D48: T0: Ideation | E48: =COUNTIF(Plan!B:B,B48) -> 1
B49: PvP Combat | C49: L | D49: T0: Ideation | E49: =COUNTIF(Plan!B:B,B49) -> 1
B50: Combat Balance & Telemetry | C50: M | D50: T2: GDD/TDD/Brief | E50: =COUNTIF(Plan!B:B,B50) -> 1
B51: Combat Abilities | C51: L | D51: T1: R&D | E51: =COUNTIF(Plan!B:B,B51) -> 1
B52: Magic | C52: L | D52: T0: Ideation | E52: =COUNTIF(Plan!B:B,B52) -> 1
B53: Full Motion Video (FMV) | C53: M | D53: T1: R&D | E53: =COUNTIF(Plan!B:B,B53) -> 1
A54: User Space
B55: User Space Server & Instance | C55: L | D55: T2: GDD/TDD/Brief | E55: =COUNTIF(Plan!B:B,B55) -> 1
B56: User Space Decoration | C56: M | D56: T0: Ideation | E56: =COUNTIF(Plan!B:B,B56) -> 1
B57: P2P / P2G User Space Connection | C57: M | D57: T2: GDD/TDD/Brief | E57: =COUNTIF(Plan!B:B,B57) -> 1
B58: Building Houses | C58: L | D58: T1: R&D | E58: =COUNTIF(Plan!B:B,B58) -> 1
B59: Saving House Layouts | C59: M | D59: T0: Ideation | E59: =COUNTIF(Plan!B:B,B59) -> 1
B60: Partner Portal System (player house) | C60: M | D60: T0: Ideation | E60: =COUNTIF(Plan!B:B,B60) -> 1
B61: Arcade Cabinet | C61: M | D61: T1: R&D | E61: =COUNTIF(Plan!B:B,B61) -> 1
B62: Anywhere Door Placement | C62: S | D62: T0: Ideation | E62: =COUNTIF(Plan!B:B,B62) -> 1
A63: Items & Inventory
B64: Item Core System | C64: L | D64: T2: GDD/TDD/Brief | E64: =COUNTIF(Plan!B:B,B64) -> 1
B65: Inventory System | C65: M | D65: T2: GDD/TDD/Brief | E65: =COUNTIF(Plan!B:B,B65) -> 1
B66: Equipment System | C66: M | D66: T0: Ideation | E66: =COUNTIF(Plan!B:B,B66) -> 1
B67: Loot Distribution | C67: M | D67: T2: GDD/TDD/Brief | E67: =COUNTIF(Plan!B:B,B67) -> 1
B68: Mounts / Pets | C68: L | D68: T1: R&D | E68: =COUNTIF(Plan!B:B,B68) -> 1
B69: Banks | C69: M | D69: T0: Ideation | E69: =COUNTIF(Plan!B:B,B69) -> 1
B70: P2P Item Transfer | C70: M | D70: T0: Ideation | E70: =COUNTIF(Plan!B:B,B70) -> 1
B71: Consumables | C71: S | D71: T2: GDD/TDD/Brief | E71: =COUNTIF(Plan!B:B,B71) -> 1
B72: Durable Items | C72: S | D72: T0: Ideation | E72: =COUNTIF(Plan!B:B,B72) -> 1
A73: Player Economy
B74: Trading System | C74: L | D74: T0: Ideation | E74: =COUNTIF(Plan!B:B,B74) -> 1
B75: Currency System | C75: M | D75: T0: Ideation | E75: =COUNTIF(Plan!B:B,B75) -> 1
B76: Auction House | C76: L | D76: T0: Ideation | E76: =COUNTIF(Plan!B:B,B76) -> 1
B77: In-game Store | C77: M | D77: T0: Ideation | E77: =COUNTIF(Plan!B:B,B77) -> 1
B78: In-game Economy | C78: L | D78: T0: Ideation | E78: =COUNTIF(Plan!B:B,B78) -> 1
B79: RMT Game Economy | C79: L | D79: T0: Ideation | E79: =COUNTIF(Plan!B:B,B79) -> 1
B80: IG / RMT Monitoring System | C80: M | D80: T0: Ideation | E80: =COUNTIF(Plan!B:B,B80) -> 1
A81: Quest System
B82: Quests Backend / Tooling | C82: L | D82: T2: GDD/TDD/Brief | E82: =COUNTIF(Plan!B:B,B82) -> 1
B83: Quests as Events | C83: M | D83: T1: R&D | E83: =COUNTIF(Plan!B:B,B83) -> 1
B84: Quest Multiplayer | C84: L | D84: T1: R&D | E84: =COUNTIF(Plan!B:B,B84) -> 1
B85: Quest Types - Courier / Escort / Kill / Collect / Mystery / Time / Partner / Lockpicking | C85: L | D85: T2: GDD/TDD/Brief | E85: =COUNTIF(Plan!B:B,B85) -> 1
B86: Quest Reward System | C86: M | D86: T0: Ideation | E86: =COUNTIF(Plan!B:B,B86) -> 1
B87: Quest Log | C87: M | D87: T0: Ideation | E87: =COUNTIF(Plan!B:B,B87) -> 1
B88: Quest Dialog GUI | C88: M | D88: T0: Ideation | E88: =COUNTIF(Plan!B:B,B88) -> 1
B89: Quest Narrative Content | C89: L | D89: T2: GDD/TDD/Brief | E89: =COUNTIF(Plan!B:B,B89) -> 1
B90: In Game Cinematic (IGC) | C90: L | D90: T2: GDD/TDD/Brief | E90: =COUNTIF(Plan!B:B,B90) -> 1
B91: Meta Quest System | C91: M | D91: T0: Ideation | E91: =COUNTIF(Plan!B:B,B91) -> 1
B92: Quest Generator System | C92: L | D92: T0: Ideation | E92: =COUNTIF(Plan!B:B,B92) -> 1
B93: Targeted VO | C93: M | D93: T2: GDD/TDD/Brief | E93: =COUNTIF(Plan!B:B,B93) -> 1
A94: Social & Multiplayer
B95: Game Chat System | C95: M | D95: T1: R&D | E95: =COUNTIF(Plan!B:B,B95) -> 1
B96: Friends | C96: M | D96: T1: R&D | E96: =COUNTIF(Plan!B:B,B96) -> 1
B97: Guilds | C97: L | D97: T1: R&D | E97: =COUNTIF(Plan!B:B,B97) -> 1
B98: Co-op / Party | C98: M | D98: T1: R&D | E98: =COUNTIF(Plan!B:B,B98) -> 1
B99: Co-op / Raids | C99: L | D99: T1: R&D | E99: =COUNTIF(Plan!B:B,B99) -> 1
B100: Dueling | C100: M | D100: T1: R&D | E100: =COUNTIF(Plan!B:B,B100) -> 1
B101: In-game Mail | C101: S | D101: T2: GDD/TDD/Brief | E101: =COUNTIF(Plan!B:B,B101) -> 1
B102: Notifications | C102: S | D102: T1: R&D | E102: =COUNTIF(Plan!B:B,B102) -> 1
B103: Player Config PvP Server | C103: M | D103: T0: Ideation | E103: =COUNTIF(Plan!B:B,B103) -> 1
B104: LFG / Pick-up Groups | C104: M | D104: T0: Ideation | E104: =COUNTIF(Plan!B:B,B104) -> 1
A105: Game Bibles
B106: UX/UI Bible | C106: M | D106: T0: Ideation | E106: =COUNTIF(Plan!B:B,B106) -> 1
B107: Accessibility Guidelines | C107: M | D107: T0: Ideation | E107: =COUNTIF(Plan!B:B,B107) -> 1
B108: Brand Bible | C108: M | D108: T2: GDD/TDD/Brief | E108: =COUNTIF(Plan!B:B,B108) -> 1
B109: Art Bible | C109: L | D109: T3: Prototype | E109: =COUNTIF(Plan!B:B,B109) -> 1
B110: Monetization Bible | C110: M | D110: T0: Ideation | E110: =COUNTIF(Plan!B:B,B110) -> 1
B111: Red Books (Live Service emergency guidelines) | C111: M | D111: T0: Ideation | E111: =COUNTIF(Plan!B:B,B111) -> 1
A112: Platform
B113: Player Account Creation / Deletion | C113: M | D113: T2: GDD/TDD/Brief | E113: =COUNTIF(Plan!B:B,B113) -> 1
B114: Player Account Authentication | C114: M | D114: T2: GDD/TDD/Brief | E114: =COUNTIF(Plan!B:B,B114) -> 1
B115: Player Account Privacy Settings & Legal | C115: M | D115: T1: R&D | E115: =COUNTIF(Plan!B:B,B115) -> 1
B116: Player Dashboard - Account Features | C116: M | D116: T1: R&D | E116: =COUNTIF(Plan!B:B,B116) -> 1
...

Sheet Resource Planner
A1: Epic | B1: Feature | C1: Story | D1: Role | E1: Team | F1: Min Days | G1: Max Days | H1: Primary Assignee | I1: Primary Days | J1: Secondary Assignee | K1: Secondary Days | L1: Unallocated
A2: Player Build
A3: Player Progression | B3: Player Progression | C3: Player level up documentation | D3: Game Designer | E3: Design | Game design | F3: 1 | G3: 14 | I3: =IF(H3="",0,G3) -> 0 | K3: 0 | L3: =G3-I3-K3 -> 14
A4: Player Progression | B4: Player Progression | C4: Player level up configuration | D4: Game Designer | E4: Design | Game design | F4: 0.5 | G4: 15 | I4: =IF(H4="",0,G4) -> 0 | K4: 0 | L4: =G4-I4-K4 -> 15
A5: Player Progression | B5: Player Progression | C5: player level up integration | D5: Gameplay Developer | E5: Engineering | Gameplay Engineering | I5: =IF(H5="",0,G5) -> 0 | K5: 0 | L5: =G5-I5-K5 -> 0
A6: Player Progression | B6: Player Progression | C6: Player level up UI | D6: UI/UX Designer | E6: Art | UX/UI | F6: 2 | G6: 3 | I6: =IF(H6="",0,G6) -> 0 | K6: 0 | L6: =G6-I6-K6 -> 3
A7: Player Progression | B7: Player Progression | C7: Character stats documentation | D7: Game Designer | E7: Design | Game design | F7: 5 | G7: 5 | I7: =IF(H7="",0,G7) -> 0 | K7: 0 | L7: =G7-I7-K7 -> 5
A8: Player Progression | B8: Player Progression | C8: Character stats implementation | D8: Gameplay Developer | E8: Engineering | Gameplay Engineering | I8: =IF(H8="",0,G8) -> 0 | K8: 0 | L8: =G8-I8-K8 -> 0
A9: Player Progression | B9: Player Progression | C9: Character stats configuration in connection with other systems | D9: Game Designer | E9: Design | Game design | F9: 1 | G9: 10 | I9: =IF(H9="",0,G9) -> 0 | K9: 0 | L9: =G9-I9-K9 -> 10
A10: Player Progression | B10: Player Progression | C10: Character stats UI | D10: UI/UX Designer | E10: Art | UX/UI | G10: 15 | I10: =IF(H10="",0,G10) -> 0 | K10: 0 | L10: =G10-I10-K10 -> 15
A11: Player Progression | B11: Player Progression | C11: Level up & Stats QA | D11: QA | E11: QA | QA | I11: =IF(H11="",0,G11) -> 0 | K11: 0 | L11: =G11-I11-K11 -> 0
A12: Player Progression | B12: Player Progression | C12: Player level up documentation | D12: Game Designer | E12: Design | Game design | I12: =IF(H12="",0,G12) -> 0 | K12: 0 | L12: =G12-I12-K12 -> 0
A13: Player Progression | B13: Player Progression | C13: Player level up configuration | D13: Game Designer | E13: Design | Game design | I13: =IF(H13="",0,G13) -> 0 | K13: 0 | L13: =G13-I13-K13 -> 0
A14: Player Progression | B14: Player Progression | C14: player level up integration | D14: Gameplay Developer | E14: Engineering | Gameplay Engineering | I14: =IF(H14="",0,G14) -> 0 | K14: 0 | L14: =G14-I14-K14 -> 0
A15: Player Progression | B15: Player Progression | C15: Earn different types of EXP depending on objective | D15: Gameplay Developer | E15: Engineering | Gameplay Engineering | F15: 2 | G15: 3 | I15: =IF(H15="",0,G15) -> 0 | K15: 0 | L15: =G15-I15-K15 -> 3
A16: Player Progression | B16: Player Progression | C16: Update player level and exp with (player data service) | D16: Backend Developer | E16: Engineering | Backend Engineering | F16: 1 | G16: 2 | I16: =IF(H16="",0,G16) -> 0 | K16: 0 | L16: =G16-I16-K16 -> 2
A17: Player Progression | B17: Player Progression | C17: Fetch player level and exp from (player data service) | D17: Backend Developer | E17: Engineering | Backend Engineering | F17: 1 | G17: 2 | I17: =IF(H17="",0,G17) -> 0 | K17: 0 | L17: =G17-I17-K17 -> 2
A18: Player Progression | B18: Player Progression | C18: Fetch and update UI for player level and exp | D18: Gameplay Developer | E18: Engineering | Gameplay Engineering | F18: 1 | G18: 2 | I18: =IF(H18="",0,G18) -> 0 | K18: 0 | L18: =G18-I18-K18 -> 2
A19: Player Progression | B19: Player Progression | C19: Player level up UI | D19: UI/UX Designer | E19: Art | UX/UI | I19: =IF(H19="",0,G19) -> 0 | K19: 0 | L19: =G19-I19-K19 -> 0
A20: Player Progression | B20: Player Progression | C20: Character stats documentation | D20: Game Designer | E20: Design | Game design | I20: =IF(H20="",0,G20) -> 0 | K20: 0 | L20: =G20-I20-K20 -> 0
A21: Player Progression | B21: Player Progression | C21: Character stats implementation | D21: Gameplay Developer | E21: Engineering | Gameplay Engineering | I21: =IF(H21="",0,G21) -> 0 | K21: 0 | L21: =G21-I21-K21 -> 0
A22: Player Progression | B22: Player Progression | C22: Increase stat when player level up | D22: Gameplay Developer | E22: Engineering | Gameplay Engineering | F22: 3 | G22: 4 | I22: =IF(H22="",0,G22) -> 0 | K22: 0 | L22: =G22-I22-K22 -> 4
A23: Player Progression | B23: Player Progression | C23: Update stats UI | D23: Gameplay Developer | E23: Engineering | Gameplay Engineering | F23: 3 | G23: 5 | I23: =IF(H23="",0,G23) -> 0 | K23: 0 | L23: =G23-I23-K23 -> 5
A24: Player Progression | B24: Player Progression | C24: Update player stats in backend (player data service) | D24: Backend Developer | E24: Engineering | Backend Engineering | F24: 1 | G24: 2 | I24: =IF(H24="",0,G24) -> 0 | K24: 0 | L24: =G24-I24-K24 -> 2
A25: Player Progression | B25: Player Progression | C25: fetch player stats from backend service (player data service) | D25: Backend Developer | E25: Engineering | Backend Engineering | F25: 1 | G25: 2 | I25: =IF(H25="",0,G25) -> 0 | K25: 0 | L25: =G25-I25-K25 -> 2
A26: Player Progression | B26: Player Progression | C26: Integrate stat system with other systems | D26: Gameplay Developer | E26: Engineering | Gameplay Engineering | F26: 1 | G26: 20 | I26: =IF(H26="",0,G26) -> 0 | K26: 0 | L26: =G26-I26-K26 -> 20
A27: Player Progression | B27: Player Progression | C27: Items give u stats | D27: Gameplay Developer | E27: Engineering | Gameplay Engineering | F27: 3 | G27: 5 | I27: =IF(H27="",0,G27) -> 0 | K27: 0 | L27: =G27-I27-K27 -> 5
A28: Player Progression | B28: Player Progression | C28: Character stats configuration in connection with other systems | D28: Game Designer | E28: Design | Game design | I28: =IF(H28="",0,G28) -> 0 | K28: 0 | L28: =G28-I28-K28 -> 0
A29: Player Progression | B29: Player Progression | C29: Character stats UI | D29: UI/UX Designer | E29: Art | UX/UI | I29: =IF(H29="",0,G29) -> 0 | K29: 0 | L29: =G29-I29-K29 -> 0
A30: Player Progression | B30: Player Progression | C30: Level up & Stats QA | D30: QA | E30: QA | QA | I30: =IF(H30="",0,G30) -> 0 | K30: 0 | L30: =G30-I30-K30 -> 0
A31: Skill System | B31: Skill System | C31: Skill Tree UI Audio | D31: Sound Designer | E31: Audio | Audio | F31: 7 | G31: 8 | I31: =IF(H31="",0,G31) -> 0 | K31: 0 | L31: =G31-I31-K31 -> 8
A32: Skill System | B32: Skill System | C32: Skills in-game audio | D32: Sound Designer | E32: Audio | Audio | F32: 7 | G32: 8 | I32: =IF(H32="",0,G32) -> 0 | K32: 0 | L32: =G32-I32-K32 -> 8
A33: Skill System | B33: Skill System | C33: Skill System Documentation | D33: Game Designer | E33: Design | Game design | F33: 4 | G33: 15 | I33: =IF(H33="",0,G33) -> 0 | K33: 0 | L33: =G33-I33-K33 -> 15
A34: Skill System | B34: Skill System | C34: Skill System Implementation | D34: Gameplay Developer | E34: Engineering | Gameplay Engineering | I34: =IF(H34="",0,G34) -> 0 | K34: 0 | L34: =G34-I34-K34 -> 0
A35: Skill System | B35: Skill System | C35: Skill System Configuration | D35: Game Designer | E35: Design | Game design | F35: 4 | G35: 5 | I35: =IF(H35="",0,G35) -> 0 | K35: 0 | L35: =G35-I35-K35 -> 5
A36: Skill System | B36: Skill System | C36: Skill System UI | D36: UI/UX Designer | E36: Art | UX/UI | I36: =IF(H36="",0,G36) -> 0 | K36: 0 | L36: =G36-I36-K36 -> 0
A37: Skill System | B37: Skill System | C37: Skill system QA | D37: QA | E37: QA | QA | I37: =IF(H37="",0,G37) -> 0 | K37: 0 | L37: =G37-I37-K37 -> 0
A38: Skill System | B38: Skill System | C38: Skill System Documentation | D38: Game Designer | E38: Design | Game design | I38: =IF(H38="",0,G38) -> 0 | K38: 0 | L38: =G38-I38-K38 -> 0
A39: Skill System | B39: Skill System | C39: Skill System Implementation | D39: Gameplay Developer | E39: Engineering | Gameplay Engineering | I39: =IF(H39="",0,G39) -> 0 | K39: 0 | L39: =G39-I39-K39 -> 0
A40: Skill System | B40: Skill System | C40: Connect skill tree to UI | D40: Gameplay Developer | E40: Engineering | Gameplay Engineering | F40: 4 | G40: 6 | I40: =IF(H40="",0,G40) -> 0 | K40: 0 | L40: =G40-I40-K40 -> 6
A41: Skill System | B41: Skill System | C41: Add new abilities to skill tree | D41: Gameplay Developer | E41: Engineering | Gameplay Engineering | F41: 2 | G41: 4 | I41: =IF(H41="",0,G41) -> 0 | K41: 0 | L41: =G41-I41-K41 -> 4
A42: Skill System | B42: Skill System | C42: Add new weapons to skill tree | D42: Gameplay Developer | E42: Engineering | Gameplay Engineering | F42: 1 | G42: 2 | I42: =IF(H42="",0,G42) -> 0 | K42: 0 | L42: =G42-I42-K42 -> 2
A43: Skill System | B43: Skill System | C43: Fetech all skill trees from backend | D43: Gameplay Developer | E43: Engineering | Gameplay Engineering | F43: 1 | G43: 2 | I43: =IF(H43="",0,G43) -> 0 | K43: 0 | L43: =G43-I43-K43 -> 2
A44: Skill System | B44: Skill System | C44: Update all skill trees from backend | D44: Gameplay Developer | E44: Engineering | Gameplay Engineering | F44: 1 | G44: 2 | I44: =IF(H44="",0,G44) -> 0 | K44: 0 | L44: =G44-I44-K44 -> 2
A45: Skill System | B45: Skill System | C45: Sync all skill trees to backend, tool | D45: Gameplay Developer | E45: Engineering | Gameplay Engineering | F45: 5 | G45: 10 | I45: =IF(H45="",0,G45) -> 0 | K45: 0 | L45: =G45-I45-K45 -> 10
A46: Skill System | B46: Skill System | C46: Create weapon skill tree / nodes in (internal dashboard service) | D46: Backend Developer | E46: Engineering | Backend Engineering | F46: 3 | G46: 4 | I46: =IF(H46="",0,G46) -> 0 | K46: 0 | L46: =G46-I46-K46 -> 4
A47: Skill System | B47: Skill System | C47: Remove weapon skill tree / nodes in (internal dashboard service) | D47: Backend Developer | E47: Engineering | Backend Engineering | F47: 1 | G47: 2 | I47: =IF(H47="",0,G47) -> 0 | K47: 0 | L47: =G47-I47-K47 -> 2
A48: Skill System | B48: Skill System | C48: Update weapon skill tree / nodes in (internal dashboard service) | D48: Backend Developer | E48: Engineering | Backend Engineering | F48: 1 | G48: 2 | I48: =IF(H48="",0,G48) -> 0 | K48: 0 | L48: =G48-I48-K48 -> 2
A49: Skill System | B49: Skill System | C49: Fetch weapon skill tree / nodes in (internal dashboard service) | D49: Backend Developer | E49: Engineering | Backend Engineering | F49: 1 | G49: 2 | I49: =IF(H49="",0,G49) -> 0 | K49: 0 | L49: =G49-I49-K49 -> 2
A50: Skill System | B50: Skill System | C50: Create new collection for weapon skill tree (player data service) | D50: Backend Developer | E50: Engineering | Backend Engineering | F50: 3 | G50: 4 | I50: =IF(H50="",0,G50) -> 0 | K50: 0 | L50: =G50-I50-K50 -> 4
A51: Skill System | B51: Skill System | C51: Update player skill tree per weapon (player data service) | D51: Backend Developer | E51: Engineering | Backend Engineering | F51: 1 | G51: 2 | I51: =IF(H51="",0,G51) -> 0 | K51: 0 | L51: =G51-I51-K51 -> 2
... A54: Skill System | B54: Skill System | C54: Create frontend for skill tree in internal dashboard | D54: Backend Developer | E54: Engineering | Backend Engineering | F54: 5 | G54: 7 | I54: =IF(H54="",0,G54) -> 0 | K54: 0 | L54: =G54-I54-K54 -> 7
A55: Skill System | B55: Skill System | C55: Skill System Configuration | D55: Game Designer | E55: Design | Game design | I55: =IF(H55="",0,G55) -> 0 | K55: 0 | L55: =G55-I55-K55 -> 0
A56: Skill System | B56: Skill System | C56: Skill System UI | D56: UI/UX Designer | E56: Art | UX/UI | I56: =IF(H56="",0,G56) -> 0 | K56: 0 | L56: =G56-I56-K56 -> 0
A57: Skill System | B57: Skill System | C57: Skill system QA | D57: QA | E57: QA | QA | I57: =IF(H57="",0,G57) -> 0 | K57: 0 | L57: =G57-I57-K57 -> 0
A58: Achievements & Trophies | B58: Achievements & Trophies | C58: Trophies | D58: Concept Artist | E58: Art | Concept Art | I58: =IF(H58="",0,G58) -> 0 | K58: 0 | L58: =G58-I58-K58 -> 0
A59: FTUE | B59: FTUE | C59: Tutorial Cave Layout Fixes | D59: Level Designer | E59: Design | Level design | F59: 7 | G59: 10 | I59: =IF(H59="",0,G59) -> 0 | K59: 0 | L59: =G59-I59-K59 -> 10
A60: FTUE | B60: FTUE | C60: Tutorial cave set dressing fixes | D60: Environment Artist | E60: Art | Environment Art | I60: =IF(H60="",0,G60) -> 0 | K60: 0 | L60: =G60-I60-K60 -> 0
A61: FTUE | B61: FTUE | C61: Tutorial Cave lighting | D61: Environment Artist | E61: Art | Environment Art | I61: =IF(H61="",0,G61) -> 0 | K61: 0 | L61: =G61-I61-K61 -> 0
A62: FTUE | B62: FTUE | C62: Tutorial cave Ambience & SFX | D62: Sound Designer | E62: Audio | Audio | F62: 5 | G62: 7 | I62: =IF(H62="",0,G62) -> 0 | K62: 0 | L62: =G62-I62-K62 -> 7
A63: FTUE | B63: FTUE | C63: Tutorial Configuration/set up/texts | D63: Game Designer | E63: Design | Game design | F63: 2 | G63: 3 | I63: =IF(H63="",0,G63) -> 0 | K63: 0 | L63: =G63-I63-K63 -> 3
A64: FTUE | B64: FTUE | C64: Tutorial UI | D64: UI/UX Designer | E64: Art | UX/UI | F64: 4 | G64: 6 | I64: =IF(H64="",0,G64) -> 0 | K64: 0 | L64: =G64-I64-K64 -> 6
A65: FTUE | B65: FTUE | C65: Tutorial VFX | D65: VFX Artist | E65: Art | VFX | I65: =IF(H65="",0,G65) -> 0 | K65: 0 | L65: =G65-I65-K65 -> 0
A66: FTUE | B66: FTUE | C66: Controls UI | D66: UI/UX Designer | E66: Art | UX/UI | F66: 2 | G66: 4 | I66: =IF(H66="",0,G66) -> 0 | K66: 0 | L66: =G66-I66-K66 -> 4
A67: FTUE | B67: FTUE | C67: Tutorial cave contents | D67: Game Designer | E67: Design | Game design | F67: 1 | G67: 2 | I67: =IF(H67="",0,G67) -> 0 | K67: 0 | L67: =G67-I67-K67 -> 2
A68: FTUE | B68: FTUE | C68: Narrative | D68: Writer | E68: Design | Narrative | F68: 0.5 | G68: 1 | I68: =IF(H68="",0,G68) -> 0 | K68: 0 | L68: =G68-I68-K68 -> 1
A69: FTUE | B69: FTUE | C69: Tutorial QA check | D69: QA | E69: QA | QA | I69: =IF(H69="",0,G69) -> 0 | K69: 0 | L69: =G69-I69-K69 -> 0
A70: FTUE | B70: FTUE | C70: Tutorial Cave Layout Fixes | D70: Level Designer | E70: Design | Level design | I70: =IF(H70="",0,G70) -> 0 | K70: 0 | L70: =G70-I70-K70 -> 0
A71: FTUE | B71: FTUE | C71: Tutorial cave set dressing fixes | D71: Environment Artist | E71: Art | Environment Art | I71: =IF(H71="",0,G71) -> 0 | K71: 0 | L71: =G71-I71-K71 -> 0
A72: FTUE | B72: FTUE | C72: Tutorial Cave lighting | D72: Environment Artist | E72: Art | Environment Art | I72: =IF(H72="",0,G72) -> 0 | K72: 0 | L72: =G72-I72-K72 -> 0
A73: FTUE | B73: FTUE | C73: Tutorial cave Ambience & SFX | D73: Sound Designer | E73: Audio | Audio | I73: =IF(H73="",0,G73) -> 0 | K73: 0 | L73: =G73-I73-K73 -> 0
A74: FTUE | B74: FTUE | C74: Tutorial Configuration/set up/texts | D74: Game Designer | E74: Design | Game design | I74: =IF(H74="",0,G74) -> 0 | K74: 0 | L74: =G74-I74-K74 -> 0
A75: FTUE | B75: FTUE | C75: Tutorial UI | D75: UI/UX Designer | E75: Art | UX/UI | I75: =IF(H75="",0,G75) -> 0 | K75: 0 | L75: =G75-I75-K75 -> 0
A76: FTUE | B76: FTUE | C76: Controls UI | D76: VFX Artist | E76: Art | VFX | I76: =IF(H76="",0,G76) -> 0 | K76: 0 | L76: =G76-I76-K76 -> 0
A77: FTUE | B77: FTUE | C77: Tutorial QA check | D77: QA | E77: QA | QA | I77: =IF(H77="",0,G77) -> 0 | K77: 0 | L77: =G77-I77-K77 -> 0
A78: FTUE | B78: FTUE | C78: FTUE Cave | D78: Environment Artist | E78: Art | Environment Art | F78: 32 | G78: 32 | I78: =IF(H78="",0,G78) -> 0 | K78: 0 | L78: =G78-I78-K78 -> 32
A79: Professions | B79: Professions | C79: Component System Design | D79: Game Designer | E79: Design | Game design | F79: 2 | G79: 5 | I79: =IF(H79="",0,G79) -> 0 | K79: 0 | L79: =G79-I79-K79 -> 5
A80: Professions | B80: Professions | C80: Crafted Weapon Parts in-game Audio | D80: Sound Designer | E80: Audio | Audio | F80: 5 | G80: 5 | I80: =IF(H80="",0,G80) -> 0 | K80: 0 | L80: =G80-I80-K80 -> 5
A81: Professions | B81: Professions | C81: Forge Crafting Audio | D81: Sound Designer | E81: Audio | Audio | F81: 3 | G81: 5 | I81: =IF(H81="",0,G81) -> 0 | K81: 0 | L81: =G81-I81-K81 -> 5
A82: Professions | B82: Professions | C82: Forge Documentation | D82: Game Designer | E82: Design | Game design | F82: 3 | G82: 5 | I82: =IF(H82="",0,G82) -> 0 | K82: 0 | L82: =G82-I82-K82 -> 5
A83: Professions | B83: Professions | C83: Forge Concepts | D83: Concept Artist | E83: Art | Concept Art | I83: =IF(H83="",0,G83) -> 0 | K83: 0 | L83: =G83-I83-K83 -> 0
A84: Professions | B84: Professions | C84: Forge Integration | D84: Gameplay Developer | E84: Engineering | Gameplay Engineering | I84: =IF(H84="",0,G84) -> 0 | K84: 0 | L84: =G84-I84-K84 -> 0
A85: Professions | B85: Professions | C85: Forge UI | D85: UI/UX Designer | E85: Art | UX/UI | F85: 5 | G85: 10 | I85: =IF(H85="",0,G85) -> 0 | K85: 0 | L85: =G85-I85-K85 -> 10
A86: Professions | B86: Professions | C86: Forge VFX | D86: VFX Artist | E86: Art | VFX | I86: =IF(H86="",0,G86) -> 0 | K86: 0 | L86: =G86-I86-K86 -> 0
A87: Professions | B87: Professions | C87: DA combination setup | D87: Technical Artist | E87: Art | TechArt | I87: =IF(H87="",0,G87) -> 0 | K87: 0 | L87: =G87-I87-K87 -> 0
A88: Professions | B88: Professions | C88: Crafting Desk | D88: Environment Artist | E88: Art | Environment Art | I88: =IF(H88="",0,G88) -> 0 | K88: 0 | L88: =G88-I88-K88 -> 0
A89: Professions | B89: Professions | C89: Forge Props | D89: Character Artist | E89: Art | Character Art | I89: =IF(H89="",0,G89) -> 0 | K89: 0 | L89: =G89-I89-K89 -> 0
A90: Professions | B90: Professions | C90: Forge QA | D90: QA | E90: QA | QA | I90: =IF(H90="",0,G90) -> 0 | K90: 0 | L90: =G90-I90-K90 -> 0
A91: Professions | B91: Professions | C91: Fishing Integration | D91: Game Designer | E91: Design | Game design | F91: 3 | G91: 3 | I91: =IF(H91="",0,G91) -> 0 | K91: 0 | L91: =G91-I91-K91 -> 3
A92: Professions | B92: Professions | C92: Fishing Rod model | D92: Environment Artist | E92: Art | Environment Art | I92: =IF(H92="",0,G92) -> 0 | K92: 0 | L92: =G92-I92-K92 -> 0
A93: Professions | B93: Professions | C93: Fish model | D93: Environment Artist | E93: Art | Environment Art | I93: =IF(H93="",0,G93) -> 0 | K93: 0 | L93: =G93-I93-K93 -> 0
A94: Professions | B94: Professions | C94: Fishing spot sign model | D94: Environment Artist | E94: Art | Environment Art | I94: =IF(H94="",0,G94) -> 0 | K94: 0 | L94: =G94-I94-K94 -> 0
A95: Professions | B95: Professions | C95: Fishing UI | D95: UI/UX Designer | E95: Art | UX/UI | G95: 3 | I95: =IF(H95="",0,G95) -> 0 | K95: 0 | L95: =G95-I95-K95 -> 3
A96: Professions | B96: Professions | C96: Fishing Spot SFX | D96: Sound Designer | E96: Audio | Audio | F96: 0 | G96: 0 | I96: =IF(H96="",0,G96) -> 0 | K96: 0 | L96: =G96-I96-K96 -> 0
A97: Professions | B97: Professions | C97: Fishing VFX | D97: VFX Artist | E97: Art | VFX | I97: =IF(H97="",0,G97) -> 0 | K97: 0 | L97: =G97-I97-K97 -> 0
A98: Professions | B98: Professions | C98: Fishing QA | D98: QA | E98: QA | QA | I98: =IF(H98="",0,G98) -> 0 | K98: 0 | L98: =G98-I98-K98 -> 0
A99: Professions | B99: Professions | C99: Forge Documentation | D99: Game Designer | E99: Design | Game design | I99: =IF(H99="",0,G99) -> 0 | K99: 0 | L99: =G99-I99-K99 -> 0
A100: Professions | B100: Professions | C100: Forge Concepts | D100: Concept Artist | E100: Art | Concept Art | I100: =IF(H100="",0,G100) -> 0 | K100: 0 | L100: =G100-I100-K100 -> 0
A101: Professions | B101: Professions | C101: Forge Integration | D101: Gameplay Developer | E101: Engineering | Gameplay Engineering | I101: =IF(H101="",0,G101) -> 0 | K101: 0 | L101: =G101-I101-K101 -> 0
A102: Professions | B102: Professions | C102: Forge UI | D102: UI/UX Designer | E102: Art | UX/UI | I102: =IF(H102="",0,G102) -> 0 | K102: 0 | L102: =G102-I102-K102 -> 0
...

Sheet Person Dashboard
A1: Person | B1: Role | C1: Department | D1: Primary Stories | E1: Primary Days | F1: Secondary Stories | G1: Secondary Days | H1: Total Days | I1: Available Days | J1: Utilisation | K1: Overloaded?
A2: Mustafa Sibai | B2: CTO | C2: Engineering | D2: =COUNTIF('Resource Planner'!H:H,"Mustafa Sibai") -> 0 | E2: =SUMPRODUCT(('Resource Planner'!H$2:H$9999="Mustafa Sibai")*'Resource Planner'!I$2:I$9999) -> 0 | F2: =COUNTIF('Resource Planner'!J:J,"Mustafa Sibai") -> 0 | G2: =SUMPRODUCT(('Resource Planner'!J$2:J$9999="Mustafa Sibai")*'Resource Planner'!K$2:K$9999) -> 0 | H2: =E2+G2 -> 0 | I2: 0 | J2: =IF(I2=0,0,H2/I2) -> 0 | K2: =IF(J2>1,"YES","")
A3: Daniel Negri | B3: Full Stack Developer | C3: Engineering | D3: =COUNTIF('Resource Planner'!H:H,"Daniel Negri") -> 0 | E3: =SUMPRODUCT(('Resource Planner'!H$2:H$9999="Daniel Negri")*'Resource Planner'!I$2:I$9999) -> 0 | F3: =COUNTIF('Resource Planner'!J:J,"Daniel Negri") -> 0 | G3: =SUMPRODUCT(('Resource Planner'!J$2:J$9999="Daniel Negri")*'Resource Planner'!K$2:K$9999) -> 0 | H3: =E3+G3 -> 0 | I3: 0 | J3: =IF(I3=0,0,H3/I3) -> 0 | K3: =IF(J3>1,"YES","")
A4: Nikos Gerontakis | B4: Full Stack Developer | C4: Engineering | D4: =COUNTIF('Resource Planner'!H:H,"Nikos Gerontakis") -> 0 | E4: =SUMPRODUCT(('Resource Planner'!H$2:H$9999="Nikos Gerontakis")*'Resource Planner'!I$2:I$9999) -> 0 | F4: =COUNTIF('Resource Planner'!J:J,"Nikos Gerontakis") -> 0 | G4: =SUMPRODUCT(('Resource Planner'!J$2:J$9999="Nikos Gerontakis")*'Resource Planner'!K$2:K$9999) -> 0 | H4: =E4+G4 -> 0 | I4: 0 | J4: =IF(I4=0,0,H4/I4) -> 0 | K4: =IF(J4>1,"YES","")
A5: Samer Balushi | B5: Backend Developer | C5: Engineering | D5: =COUNTIF('Resource Planner'!H:H,"Samer Balushi") -> 0 | E5: =SUMPRODUCT(('Resource Planner'!H$2:H$9999="Samer Balushi")*'Resource Planner'!I$2:I$9999) -> 0 | F5: =COUNTIF('Resource Planner'!J:J,"Samer Balushi") -> 0 | G5: =SUMPRODUCT(('Resource Planner'!J$2:J$9999="Samer Balushi")*'Resource Planner'!K$2:K$9999) -> 0 | H5: =E5+G5 -> 0 | I5: 0 | J5: =IF(I5=0,0,H5/I5) -> 0 | K5: =IF(J5>1,"YES","")
A6: Raynor D'Souza | B6: Gameplay Developer | C6: Engineering | D6: =COUNTIF('Resource Planner'!H:H,"Raynor D'Souza") -> 0 | E6: =SUMPRODUCT(('Resource Planner'!H$2:H$9999="Raynor D'Souza")*'Resource Planner'!I$2:I$9999) -> 0 | F6: =COUNTIF('Resource Planner'!J:J,"Raynor D'Souza") -> 0 | G6: =SUMPRODUCT(('Resource Planner'!J$2:J$9999="Raynor D'Souza")*'Resource Planner'!K$2:K$9999) -> 0 | H6: =E6+G6 -> 0 | I6: 0 | J6: =IF(I6=0,0,H6/I6) -> 0 | K6: =IF(J6>1,"YES","")
A7: Ilya Achmetov | B7: Gameplay Developer | C7: Engineering | D7: =COUNTIF('Resource Planner'!H:H,"Ilya Achmetov") -> 0 | E7: =SUMPRODUCT(('Resource Planner'!H$2:H$9999="Ilya Achmetov")*'Resource Planner'!I$2:I$9999) -> 0 | F7: =COUNTIF('Resource Planner'!J:J,"Ilya Achmetov") -> 0 | G7: =SUMPRODUCT(('Resource Planner'!J$2:J$9999="Ilya Achmetov")*'Resource Planner'!K$2:K$9999) -> 0 | H7: =E7+G7 -> 0 | I7: 0 | J7: =IF(I7=0,0,H7/I7) -> 0 | K7: =IF(J7>1,"YES","")
A8: Leon Huang | B8: Gameplay Developer | C8: Engineering | D8: =COUNTIF('Resource Planner'!H:H,"Leon Huang") -> 0 | E8: =SUMPRODUCT(('Resource Planner'!H$2:H$9999="Leon Huang")*'Resource Planner'!I$2:I$9999) -> 0 | F8: =COUNTIF('Resource Planner'!J:J,"Leon Huang") -> 0 | G8: =SUMPRODUCT(('Resource Planner'!J$2:J$9999="Leon Huang")*'Resource Planner'!K$2:K$9999) -> 0 | H8: =E8+G8 -> 0 | I8: 0 | J8: =IF(I8=0,0,H8/I8) -> 0 | K8: =IF(J8>1,"YES","")
A9: Ignasi Ezpeleta | B9: Gameplay Developer | C9: Engineering | D9: =COUNTIF('Resource Planner'!H:H,"Ignasi Ezpeleta") -> 0 | E9: =SUMPRODUCT(('Resource Planner'!H$2:H$9999="Ignasi Ezpeleta")*'Resource Planner'!I$2:I$9999) -> 0 | F9: =COUNTIF('Resource Planner'!J:J,"Ignasi Ezpeleta") -> 0 | G9: =SUMPRODUCT(('Resource Planner'!J$2:J$9999="Ignasi Ezpeleta")*'Resource Planner'!K$2:K$9999) -> 0 | H9: =E9+G9 -> 0 | I9: 0 | J9: =IF(I9=0,0,H9/I9) -> 0 | K9: =IF(J9>1,"YES","")
A10: Roberto | B10: Gameplay Developer | C10: Engineering | D10: =COUNTIF('Resource Planner'!H:H,"Roberto") -> 0 | E10: =SUMPRODUCT(('Resource Planner'!H$2:H$9999="Roberto")*'Resource Planner'!I$2:I$9999) -> 0 | F10: =COUNTIF('Resource Planner'!J:J,"Roberto") -> 0 | G10: =SUMPRODUCT(('Resource Planner'!J$2:J$9999="Roberto")*'Resource Planner'!K$2:K$9999) -> 0 | H10: =E10+G10 -> 0 | I10: 0 | J10: =IF(I10=0,0,H10/I10) -> 0 | K10: =IF(J10>1,"YES","")
A11: Matt | B11: Animator | C11: Engineering | D11: =COUNTIF('Resource Planner'!H:H,"Matt") -> 0 | E11: =SUMPRODUCT(('Resource Planner'!H$2:H$9999="Matt")*'Resource Planner'!I$2:I$9999) -> 0 | F11: =COUNTIF('Resource Planner'!J:J,"Matt") -> 0 | G11: =SUMPRODUCT(('Resource Planner'!J$2:J$9999="Matt")*'Resource Planner'!K$2:K$9999) -> 0 | H11: =E11+G11 -> 0 | I11: 0 | J11: =IF(I11=0,0,H11/I11) -> 0 | K11: =IF(J11>1,"YES","")
A12: David Luong | B12: Art Director | C12: Art | D12: =COUNTIF('Resource Planner'!H:H,"David Luong") -> 0 | E12: =SUMPRODUCT(('Resource Planner'!H$2:H$9999="David Luong")*'Resource Planner'!I$2:I$9999) -> 0 | F12: =COUNTIF('Resource Planner'!J:J,"David Luong") -> 0 | G12: =SUMPRODUCT(('Resource Planner'!J$2:J$9999="David Luong")*'Resource Planner'!K$2:K$9999) -> 0 | H12: =E12+G12 -> 0 | I12: 0 | J12: =IF(I12=0,0,H12/I12) -> 0 | K12: =IF(J12>1,"YES","")
A13: Wojciech Szon | B13: VFX Artist | C13: Art | D13: =COUNTIF('Resource Planner'!H:H,"Wojciech Szon") -> 0 | E13: =SUMPRODUCT(('Resource Planner'!H$2:H$9999="Wojciech Szon")*'Resource Planner'!I$2:I$9999) -> 0 | F13: =COUNTIF('Resource Planner'!J:J,"Wojciech Szon") -> 0 | G13: =SUMPRODUCT(('Resource Planner'!J$2:J$9999="Wojciech Szon")*'Resource Planner'!K$2:K$9999) -> 0 | H13: =E13+G13 -> 0 | I13: 0 | J13: =IF(I13=0,0,H13/I13) -> 0 | K13: =IF(J13>1,"YES","")
A14: Conor McLean | B14: VFX Artist | C14: Art | D14: =COUNTIF('Resource Planner'!H:H,"Conor McLean") -> 0 | E14: =SUMPRODUCT(('Resource Planner'!H$2:H$9999="Conor McLean")*'Resource Planner'!I$2:I$9999) -> 0 | F14: =COUNTIF('Resource Planner'!J:J,"Conor McLean") -> 0 | G14: =SUMPRODUCT(('Resource Planner'!J$2:J$9999="Conor McLean")*'Resource Planner'!K$2:K$9999) -> 0 | H14: =E14+G14 -> 0 | I14: 0 | J14: =IF(I14=0,0,H14/I14) -> 0 | K14: =IF(J14>1,"YES","")
A15: Michail Velissaris | B15: VFX Artist | C15: Art | D15: =COUNTIF('Resource Planner'!H:H,"Michail Velissaris") -> 0 | E15: =SUMPRODUCT(('Resource Planner'!H$2:H$9999="Michail Velissaris")*'Resource Planner'!I$2:I$9999) -> 0 | F15: =COUNTIF('Resource Planner'!J:J,"Michail Velissaris") -> 0 | G15: =SUMPRODUCT(('Resource Planner'!J$2:J$9999="Michail Velissaris")*'Resource Planner'!K$2:K$9999) -> 0 | H15: =E15+G15 -> 0 | I15: 0 | J15: =IF(I15=0,0,H15/I15) -> 0 | K15: =IF(J15>1,"YES","")
A16: Stefano Vietina | B16: Technical Artist | C16: Art | D16: =COUNTIF('Resource Planner'!H:H,"Stefano Vietina") -> 0 | E16: =SUMPRODUCT(('Resource Planner'!H$2:H$9999="Stefano Vietina")*'Resource Planner'!I$2:I$9999) -> 0 | F16: =COUNTIF('Resource Planner'!J:J,"Stefano Vietina") -> 0 | G16: =SUMPRODUCT(('Resource Planner'!J$2:J$9999="Stefano Vietina")*'Resource Planner'!K$2:K$9999) -> 0 | H16: =E16+G16 -> 0 | I16: 0 | J16: =IF(I16=0,0,H16/I16) -> 0 | K16: =IF(J16>1,"YES","")
A17: Samuele Piazzi | B17: Technical Artist | C17: Art | D17: =COUNTIF('Resource Planner'!H:H,"Samuele Piazzi") -> 0 | E17: =SUMPRODUCT(('Resource Planner'!H$2:H$9999="Samuele Piazzi")*'Resource Planner'!I$2:I$9999) -> 0 | F17: =COUNTIF('Resource Planner'!J:J,"Samuele Piazzi") -> 0 | G17: =SUMPRODUCT(('Resource Planner'!J$2:J$9999="Samuele Piazzi")*'Resource Planner'!K$2:K$9999) -> 0 | H17: =E17+G17 -> 0 | I17: 0 | J17: =IF(I17=0,0,H17/I17) -> 0 | K17: =IF(J17>1,"YES","")
A18: Andrea Rottini | B18: Technical Artist | C18: Art | D18: =COUNTIF('Resource Planner'!H:H,"Andrea Rottini") -> 0 | E18: =SUMPRODUCT(('Resource Planner'!H$2:H$9999="Andrea Rottini")*'Resource Planner'!I$2:I$9999) -> 0 | F18: =COUNTIF('Resource Planner'!J:J,"Andrea Rottini") -> 0 | G18: =SUMPRODUCT(('Resource Planner'!J$2:J$9999="Andrea Rottini")*'Resource Planner'!K$2:K$9999) -> 0 | H18: =E18+G18 -> 0 | I18: 0 | J18: =IF(I18=0,0,H18/I18) -> 0 | K18: =IF(J18>1,"YES","")
A19: Niko Gesell | B19: Concept Artist | C19: Art | D19: =COUNTIF('Resource Planner'!H:H,"Niko Gesell") -> 0 | E19: =SUMPRODUCT(('Resource Planner'!H$2:H$9999="Niko Gesell")*'Resource Planner'!I$2:I$9999) -> 0 | F19: =COUNTIF('Resource Planner'!J:J,"Niko Gesell") -> 0 | G19: =SUMPRODUCT(('Resource Planner'!J$2:J$9999="Niko Gesell")*'Resource Planner'!K$2:K$9999) -> 0 | H19: =E19+G19 -> 0 | I19: 0 | J19: =IF(I19=0,0,H19/I19) -> 0 | K19: =IF(J19>1,"YES","")
A20: Kerim Turay | B20: Concept Artist | C20: Art | D20: =COUNTIF('Resource Planner'!H:H,"Kerim Turay") -> 0 | E20: =SUMPRODUCT(('Resource Planner'!H$2:H$9999="Kerim Turay")*'Resource Planner'!I$2:I$9999) -> 0 | F20: =COUNTIF('Resource Planner'!J:J,"Kerim Turay") -> 0 | G20: =SUMPRODUCT(('Resource Planner'!J$2:J$9999="Kerim Turay")*'Resource Planner'!K$2:K$9999) -> 0 | H20: =E20+G20 -> 0 | I20: 0 | J20: =IF(I20=0,0,H20/I20) -> 0 | K20: =IF(J20>1,"YES","")
A21: Gerard Vicen | B21: Concept Artist | C21: Art | D21: =COUNTIF('Resource Planner'!H:H,"Gerard Vicen") -> 0 | E21: =SUMPRODUCT(('Resource Planner'!H$2:H$9999="Gerard Vicen")*'Resource Planner'!I$2:I$9999) -> 0 | F21: =COUNTIF('Resource Planner'!J:J,"Gerard Vicen") -> 0 | G21: =SUMPRODUCT(('Resource Planner'!J$2:J$9999="Gerard Vicen")*'Resource Planner'!K$2:K$9999) -> 0 | H21: =E21+G21 -> 0 | I21: 0 | J21: =IF(I21=0,0,H21/I21) -> 0 | K21: =IF(J21>1,"YES","")
A22: Julian Hartinger | B22: Concept Artist | C22: Art | D22: =COUNTIF('Resource Planner'!H:H,"Julian Hartinger") -> 0 | E22: =SUMPRODUCT(('Resource Planner'!H$2:H$9999="Julian Hartinger")*'Resource Planner'!I$2:I$9999) -> 0 | F22: =COUNTIF('Resource Planner'!J:J,"Julian Hartinger") -> 0 | G22: =SUMPRODUCT(('Resource Planner'!J$2:J$9999="Julian Hartinger")*'Resource Planner'!K$2:K$9999) -> 0 | H22: =E22+G22 -> 0 | I22: 0 | J22: =IF(I22=0,0,H22/I22) -> 0 | K22: =IF(J22>1,"YES","")
A23: Gianluca Perusi | B23: UI/UX Designer | C23: Art | D23: =COUNTIF('Resource Planner'!H:H,"Gianluca Perusi") -> 0 | E23: =SUMPRODUCT(('Resource Planner'!H$2:H$9999="Gianluca Perusi")*'Resource Planner'!I$2:I$9999) -> 0 | F23: =COUNTIF('Resource Planner'!J:J,"Gianluca Perusi") -> 0 | G23: =SUMPRODUCT(('Resource Planner'!J$2:J$9999="Gianluca Perusi")*'Resource Planner'!K$2:K$9999) -> 0 | H23: =E23+G23 -> 0 | I23: 0 | J23: =IF(I23=0,0,H23/I23) -> 0 | K23: =IF(J23>1,"YES","")
A24: Larisa Logofatu | B24: Graphic Designer | C24: Art | D24: =COUNTIF('Resource Planner'!H:H,"Larisa Logofatu") -> 0 | E24: =SUMPRODUCT(('Resource Planner'!H$2:H$9999="Larisa Logofatu")*'Resource Planner'!I$2:I$9999) -> 0 | F24: =COUNTIF('Resource Planner'!J:J,"Larisa Logofatu") -> 0 | G24: =SUMPRODUCT(('Resource Planner'!J$2:J$9999="Larisa Logofatu")*'Resource Planner'!K$2:K$9999) -> 0 | H24: =E24+G24 -> 0 | I24: 0 | J24: =IF(I24=0,0,H24/I24) -> 0 | K24: =IF(J24>1,"YES","")
A25: Alon | B25: Animator | C25: Art | D25: =COUNTIF('Resource Planner'!H:H,"Alon") -> 0 | E25: =SUMPRODUCT(('Resource Planner'!H$2:H$9999="Alon")*'Resource Planner'!I$2:I$9999) -> 0 | F25: =COUNTIF('Resource Planner'!J:J,"Alon") -> 0 | G25: =SUMPRODUCT(('Resource Planner'!J$2:J$9999="Alon")*'Resource Planner'!K$2:K$9999) -> 0 | H25: =E25+G25 -> 0 | I25: 0 | J25: =IF(I25=0,0,H25/I25) -> 0 | K25: =IF(J25>1,"YES","")
A26: Kunjal Asher | B26: Animator | C26: Art | D26: =COUNTIF('Resource Planner'!H:H,"Kunjal Asher") -> 0 | E26: =SUMPRODUCT(('Resource Planner'!H$2:H$9999="Kunjal Asher")*'Resource Planner'!I$2:I$9999) -> 0 | F26: =COUNTIF('Resource Planner'!J:J,"Kunjal Asher") -> 0 | G26: =SUMPRODUCT(('Resource Planner'!J$2:J$9999="Kunjal Asher")*'Resource Planner'!K$2:K$9999) -> 0 | H26: =E26+G26 -> 0 | I26: 0 | J26: =IF(I26=0,0,H26/I26) -> 0 | K26: =IF(J26>1,"YES","")
A27: Maddalena Morello | B27: Character Rigger | C27: Art | D27: =COUNTIF('Resource Planner'!H:H,"Maddalena Morello") -> 0 | E27: =SUMPRODUCT(('Resource Planner'!H$2:H$9999="Maddalena Morello")*'Resource Planner'!I$2:I$9999) -> 0 | F27: =COUNTIF('Resource Planner'!J:J,"Maddalena Morello") -> 0 | G27: =SUMPRODUCT(('Resource Planner'!J$2:J$9999="Maddalena Morello")*'Resource Planner'!K$2:K$9999) -> 0 | H27: =E27+G27 -> 0 | I27: 0 | J27: =IF(I27=0,0,H27/I27) -> 0 | K27: =IF(J27>1,"YES","")
A28: Sasha Krieger | B28: Character Artist | C28: Art | D28: =COUNTIF('Resource Planner'!H:H,"Sasha Krieger") -> 0 | E28: =SUMPRODUCT(('Resource Planner'!H$2:H$9999="Sasha Krieger")*'Resource Planner'!I$2:I$9999) -> 0 | F28: =COUNTIF('Resource Planner'!J:J,"Sasha Krieger") -> 0 | G28: =SUMPRODUCT(('Resource Planner'!J$2:J$9999="Sasha Krieger")*'Resource Planner'!K$2:K$9999) -> 0 | H28: =E28+G28 -> 0 | I28: 0 | J28: =IF(I28=0,0,H28/I28) -> 0 | K28: =IF(J28>1,"YES","")
A29: Dimitris Chrysanthakopoulos | B29: Character Artist | C29: Art | D29: =COUNTIF('Resource Planner'!H:H,"Dimitris Chrysanthakopoulos") -> 0 | E29: =SUMPRODUCT(('Resource Planner'!H$2:H$9999="Dimitris Chrysanthakopoulos")*'Resource Planner'!I$2:I$9999) -> 0 | F29: =COUNTIF('Resource Planner'!J:J,"Dimitris Chrysanthakopoulos") -> 0 | G29: =SUMPRODUCT(('Resource Planner'!J$2:J$9999="Dimitris Chrysanthakopoulos")*'Resource Planner'!K$2:K$9999) -> 0 | H29: =E29+G29 -> 0 | I29: 0 | J29: =IF(I29=0,0,H29/I29) -> 0 | K29: =IF(J29>1,"YES","")
A30: Rebecca Tomasoni | B30: Character Artist | C30: Art | D30: =COUNTIF('Resource Planner'!H:H,"Rebecca Tomasoni") -> 0 | E30: =SUMPRODUCT(('Resource Planner'!H$2:H$9999="Rebecca Tomasoni")*'Resource Planner'!I$2:I$9999) -> 0 | F30: =COUNTIF('Resource Planner'!J:J,"Rebecca Tomasoni") -> 0 | G30: =SUMPRODUCT(('Resource Planner'!J$2:J$9999="Rebecca Tomasoni")*'Resource Planner'!K$2:K$9999) -> 0 | H30: =E30+G30 -> 0 | I30: 0 | J30: =IF(I30=0,0,H30/I30) -> 0 | K30: =IF(J30>1,"YES","")
A31: Michael Dunnam | B31: Environment Artist | C31: Art | D31: =COUNTIF('Resource Planner'!H:H,"Michael Dunnam") -> 0 | E31: =SUMPRODUCT(('Resource Planner'!H$2:H$9999="Michael Dunnam")*'Resource Planner'!I$2:I$9999) -> 0 | F31: =COUNTIF('Resource Planner'!J:J,"Michael Dunnam") -> 0 | G31: =SUMPRODUCT(('Resource Planner'!J$2:J$9999="Michael Dunnam")*'Resource Planner'!K$2:K$9999) -> 0 | H31: =E31+G31 -> 0 | I31: 0 | J31: =IF(I31=0,0,H31/I31) -> 0 | K31: =IF(J31>1,"YES","")
A32: Ella Amatooni | B32: Environment Artist | C32: Art | D32: =COUNTIF('Resource Planner'!H:H,"Ella Amatooni") -> 0 | E32: =SUMPRODUCT(('Resource Planner'!H$2:H$9999="Ella Amatooni")*'Resource Planner'!I$2:I$9999) -> 0 | F32: =COUNTIF('Resource Planner'!J:J,"Ella Amatooni") -> 0 | G32: =SUMPRODUCT(('Resource Planner'!J$2:J$9999="Ella Amatooni")*'Resource Planner'!K$2:K$9999) -> 0 | H32: =E32+G32 -> 0 | I32: 0 | J32: =IF(I32=0,0,H32/I32) -> 0 | K32: =IF(J32>1,"YES","")
A33: Marc Vives | B33: Environment Artist | C33: Art | D33: =COUNTIF('Resource Planner'!H:H,"Marc Vives") -> 0 | E33: =SUMPRODUCT(('Resource Planner'!H$2:H$9999="Marc Vives")*'Resource Planner'!I$2:I$9999) -> 0 | F33: =COUNTIF('Resource Planner'!J:J,"Marc Vives") -> 0 | G33: =SUMPRODUCT(('Resource Planner'!J$2:J$9999="Marc Vives")*'Resource Planner'!K$2:K$9999) -> 0 | H33: =E33+G33 -> 0 | I33: 0 | J33: =IF(I33=0,0,H33/I33) -> 0 | K33: =IF(J33>1,"YES","")
A34: Iosif Alexiou | B34: Environment Artist | C34: Art | D34: =COUNTIF('Resource Planner'!H:H,"Iosif Alexiou") -> 0 | E34: =SUMPRODUCT(('Resource Planner'!H$2:H$9999="Iosif Alexiou")*'Resource Planner'!I$2:I$9999) -> 0 | F34: =COUNTIF('Resource Planner'!J:J,"Iosif Alexiou") -> 0 | G34: =SUMPRODUCT(('Resource Planner'!J$2:J$9999="Iosif Alexiou")*'Resource Planner'!K$2:K$9999) -> 0 | H34: =E34+G34 -> 0 | I34: 0 | J34: =IF(I34=0,0,H34/I34) -> 0 | K34: =IF(J34>1,"YES","")
A35: Nick Chrysanthakopoulos | B35: Prop Artist | C35: Art | D35: =COUNTIF('Resource Planner'!H:H,"Nick Chrysanthakopoulos") -> 0 | E35: =SUMPRODUCT(('Resource Planner'!H$2:H$9999="Nick Chrysanthakopoulos")*'Resource Planner'!I$2:I$9999) -> 0 | F35: =COUNTIF('Resource Planner'!J:J,"Nick Chrysanthakopoulos") -> 0 | G35: =SUMPRODUCT(('Resource Planner'!J$2:J$9999="Nick Chrysanthakopoulos")*'Resource Planner'!K$2:K$9999) -> 0 | H35: =E35+G35 -> 0 | I35: 0 | J35: =IF(I35=0,0,H35/I35) -> 0 | K35: =IF(J35>1,"YES","")
A36: Chris Brough | B36: Environment Artist | C36: Art | D36: =COUNTIF('Resource Planner'!H:H,"Chris Brough") -> 0 | E36: =SUMPRODUCT(('Resource Planner'!H$2:H$9999="Chris Brough")*'Resource Planner'!I$2:I$9999) -> 0 | F36: =COUNTIF('Resource Planner'!J:J,"Chris Brough") -> 0 | G36: =SUMPRODUCT(('Resource Planner'!J$2:J$9999="Chris Brough")*'Resource Planner'!K$2:K$9999) -> 0 | H36: =E36+G36 -> 0 | I36: 0 | J36: =IF(I36=0,0,H36/I36) -> 0 | K36: =IF(J36>1,"YES","")
A37: Robin Jubber | B37: Game Director | C37: Design | D37: =COUNTIF('Resource Planner'!H:H,"Robin Jubber") -> 0 | E37: =SUMPRODUCT(('Resource Planner'!H$2:H$9999="Robin Jubber")*'Resource Planner'!I$2:I$9999) -> 0 | F37: =COUNTIF('Resource Planner'!J:J,"Robin Jubber") -> 0 | G37: =SUMPRODUCT(('Resource Planner'!J$2:J$9999="Robin Jubber")*'Resource Planner'!K$2:K$9999) -> 0 | H37: =E37+G37 -> 0 | I37: 0 | J37: =IF(I37=0,0,H37/I37) -> 0 | K37: =IF(J37>1,"YES","")
A38: Yorgos Dritsas | B38: Game Designer | C38: Design | D38: =COUNTIF('Resource Planner'!H:H,"Yorgos Dritsas") -> 0 | E38: =SUMPRODUCT(('Resource Planner'!H$2:H$9999="Yorgos Dritsas")*'Resource Planner'!I$2:I$9999) -> 0 | F38: =COUNTIF('Resource Planner'!J:J,"Yorgos Dritsas") -> 0 | G38: =SUMPRODUCT(('Resource Planner'!J$2:J$9999="Yorgos Dritsas")*'Resource Planner'!K$2:K$9999) -> 0 | H38: =E38+G38 -> 0 | I38: 0 | J38: =IF(I38=0,0,H38/I38) -> 0 | K38: =IF(J38>1,"YES","")
A39: Nadir Latif | B39: Combat Designer | C39: Design | D39: =COUNTIF('Resource Planner'!H:H,"Nadir Latif") -> 0 | E39: =SUMPRODUCT(('Resource Planner'!H$2:H$9999="Nadir Latif")*'Resource Planner'!I$2:I$9999) -> 0 | F39: =COUNTIF('Resource Planner'!J:J,"Nadir Latif") -> 0 | G39: =SUMPRODUCT(('Resource Planner'!J$2:J$9999="Nadir Latif")*'Resource Planner'!K$2:K$9999) -> 0 | H39: =E39+G39 -> 0 | I39: 0 | J39: =IF(I39=0,0,H39/I39) -> 0 | K39: =IF(J39>1,"YES","")
A40: Kieron Naylor | B40: Technical Designer | C40: Design | D40: =COUNTIF('Resource Planner'!H:H,"Kieron Naylor") -> 0 | E40: =SUMPRODUCT(('Resource Planner'!H$2:H$9999="Kieron Naylor")*'Resource Planner'!I$2:I$9999) -> 0 | F40: =COUNTIF('Resource Planner'!J:J,"Kieron Naylor") -> 0 | G40: =SUMPRODUCT(('Resource Planner'!J$2:J$9999="Kieron Naylor")*'Resource Planner'!K$2:K$9999) -> 0 | H40: =E40+G40 -> 0 | I40: 0 | J40: =IF(I40=0,0,H40/I40) -> 0 | K40: =IF(J40>1,"YES","")
A41: Nikolas Tziotis | B41: Level Designer | C41: Design | D41: =COUNTIF('Resource Planner'!H:H,"Nikolas Tziotis") -> 0 | E41: =SUMPRODUCT(('Resource Planner'!H$2:H$9999="Nikolas Tziotis")*'Resource Planner'!I$2:I$9999) -> 0 | F41: =COUNTIF('Resource Planner'!J:J,"Nikolas Tziotis") -> 0 | G41: =SUMPRODUCT(('Resource Planner'!J$2:J$9999="Nikolas Tziotis")*'Resource Planner'!K$2:K$9999) -> 0 | H41: =E41+G41 -> 0 | I41: 0 | J41: =IF(I41=0,0,H41/I41) -> 0 | K41: =IF(J41>1,"YES","")
A42: Seth Dahl | B42: Level Designer | C42: Design | D42: =COUNTIF('Resource Planner'!H:H,"Seth Dahl") -> 0 | E42: =SUMPRODUCT(('Resource Planner'!H$2:H$9999="Seth Dahl")*'Resource Planner'!I$2:I$9999) -> 0 | F42: =COUNTIF('Resource Planner'!J:J,"Seth Dahl") -> 0 | G42: =SUMPRODUCT(('Resource Planner'!J$2:J$9999="Seth Dahl")*'Resource Planner'!K$2:K$9999) -> 0 | H42: =E42+G42 -> 0 | I42: 0 | J42: =IF(I42=0,0,H42/I42) -> 0 | K42: =IF(J42>1,"YES","")
A43: Panos Andriopoulos | B43: Level Designer | C43: Design | D43: =COUNTIF('Resource Planner'!H:H,"Panos Andriopoulos") -> 0 | E43: =SUMPRODUCT(('Resource Planner'!H$2:H$9999="Panos Andriopoulos")*'Resource Planner'!I$2:I$9999) -> 0 | F43: =COUNTIF('Resource Planner'!J:J,"Panos Andriopoulos") -> 0 | G43: =SUMPRODUCT(('Resource Planner'!J$2:J$9999="Panos Andriopoulos")*'Resource Planner'!K$2:K$9999) -> 0 | H43: =E43+G43 -> 0 | I43: 0 | J43: =IF(I43=0,0,H43/I43) -> 0 | K43: =IF(J43>1,"YES","")
A44: Maria Cibej | B44: Writer | C44: Design | D44: =COUNTIF('Resource Planner'!H:H,"Maria Cibej") -> 0 | E44: =SUMPRODUCT(('Resource Planner'!H$2:H$9999="Maria Cibej")*'Resource Planner'!I$2:I$9999) -> 0 | F44: =COUNTIF('Resource Planner'!J:J,"Maria Cibej") -> 0 | G44: =SUMPRODUCT(('Resource Planner'!J$2:J$9999="Maria Cibej")*'Resource Planner'!K$2:K$9999) -> 0 | H44: =E44+G44 -> 0 | I44: 0 | J44: =IF(I44=0,0,H44/I44) -> 0 | K44: =IF(J44>1,"YES","")
A45: Dragan Vuckovic | B45: Sound Designer | C45: Audio | D45: =COUNTIF('Resource Planner'!H:H,"Dragan Vuckovic") -> 0 | E45: =SUMPRODUCT(('Resource Planner'!H$2:H$9999="Dragan Vuckovic")*'Resource Planner'!I$2:I$9999) -> 0 | F45: =COUNTIF('Resource Planner'!J:J,"Dragan Vuckovic") -> 0 | G45: =SUMPRODUCT(('Resource Planner'!J$2:J$9999="Dragan Vuckovic")*'Resource Planner'!K$2:K$9999) -> 0 | H45: =E45+G45 -> 0 | I45: 0 | J45: =IF(I45=0,0,H45/I45) -> 0 | K45: =IF(J45>1,"YES","")
A46: Aggeliki Peroutsea | B46: Sound Designer | C46: Audio | D46: =COUNTIF('Resource Planner'!H:H,"Aggeliki Peroutsea") -> 0 | E46: =SUMPRODUCT(('Resource Planner'!H$2:H$9999="Aggeliki Peroutsea")*'Resource Planner'!I$2:I$9999) -> 0 | F46: =COUNTIF('Resource Planner'!J:J,"Aggeliki Peroutsea") -> 0 | G46: =SUMPRODUCT(('Resource Planner'!J$2:J$9999="Aggeliki Peroutsea")*'Resource Planner'!K$2:K$9999) -> 0 | H46: =E46+G46 -> 0 | I46: 0 | J46: =IF(I46=0,0,H46/I46) -> 0 | K46: =IF(J46>1,"YES","")
A47: Hannah Pickard | B47: QA | C47: QA | D47: =COUNTIF('Resource Planner'!H:H,"Hannah Pickard") -> 0 | E47: =SUMPRODUCT(('Resource Planner'!H$2:H$9999="Hannah Pickard")*'Resource Planner'!I$2:I$9999) -> 0 | F47: =COUNTIF('Resource Planner'!J:J,"Hannah Pickard") -> 0 | G47: =SUMPRODUCT(('Resource Planner'!J$2:J$9999="Hannah Pickard")*'Resource Planner'!K$2:K$9999) -> 0 | H47: =E47+G47 -> 0 | I47: 0 | J47: =IF(I47=0,0,H47/I47) -> 0 | K47: =IF(J47>1,"YES","")

Sheet Feature Timeline
A1: Epic | B1: Feature | C1: Total Stories | D1: Total Max Days | E1: Roles Involved
A2: Player Build
A3: Player Build | B3: Player Progression | C3: 28 | D3: 109 | E3: Backend Developer, Game Designer, Gameplay Developer, QA, UI/UX Designer
A4: Player Build | B4: Skill System | C4: 27 | D4: 90 | E4: Backend Developer, Game Designer, Gameplay Developer, QA, Sound Designer, UI/UX Designer
A5: Player Build | B5: Achievements & Trophies | C5: 1 | D5: 0 | E5: Concept Artist
A6: Player Build | B6: FTUE | C6: 20 | D6: 65 | E6: Environment Artist, Game Designer, Level Designer, QA, Sound Designer, UI/UX Designer, VFX Artist, Writer
A7: Player Build | B7: Professions | C7: 39 | D7: 39 | E7: Character Artist, Concept Artist, Environment Artist, Game Designer, Gameplay Developer, QA, Sound Designer, Technical Artist, UI/UX Designer, VFX Artist
A8: Player Build | B8: Character Creation & Customization | C8: 9 | D8: 0 | E8: Character Artist, Concept Artist
A9: Player Build | B9: Garment System | C9: 32 | D9: 74 | E9: Animator, Character Artist, Concept Artist, Game Designer, Gameplay Developer, QA, Sound Designer, Technical Artist, UI/UX Designer
A10: World Systems
A11: World Systems | B11: Foam Corruption | C11: 55 | D11: 50 | E11: Animator, Backend Developer, Character Artist, Environment Artist, Game Designer, Gameplay Developer, QA, Sound Designer, Technical Artist, VFX Artist, Writer
A12: World Systems | B12: Basic Movement System | C12: 15 | D12: 10 | E12: Game Designer, Gameplay Developer, QA
A13: World Systems | B13: Advanced Traversal | C13: 43 | D13: 46 | E13: Animator, Backend Developer, Character Artist, Concept Artist, Environment Artist, Game Designer, Gameplay Developer, QA, Sound Designer, UI/UX Designer, VFX Artist, Writer
A14: World Systems | B14: Navigation | C14: 59 | D14: 113 | E14: Backend Developer, Concept Artist, Environment Artist, Game Designer, Gameplay Developer, QA, Sound Designer, Technical Artist, UI/UX Designer
A15: World Systems | B15: Instancing | C15: 48 | D15: 90 | E15: Backend Developer, Game Designer, Gameplay Developer, QA
A16: World Systems | B16: Dungeon Mechanics | C16: 62 | D16: 123.1 | E16: Backend Developer, Character Artist, Concept Artist, Environment Artist, Game Designer, Gameplay Developer, Level Designer, QA, Sound Designer, Technical Artist, UI/UX Designer, VFX Artist, Writer
A17: World Systems | B17: The Dungeon | C17: 1 | D17: 68.6 | E17: Environment Artist
A18: World Systems | B18: Partner Portal | C18: 9 | D18: 27 | E18: Backend Developer, Environment Artist, Game Designer, Gameplay Developer, VFX Artist
A19: World Systems | B19: Biome - Portal Peak | C19: 55 | D19: 665.8 | E19: Concept Artist, Environment Artist, Game Designer, Level Designer, QA, Sound Designer
A20: World Systems | B20: Biome - Hidden Hills | C20: 17 | D20: 115.4 | E20: Concept Artist, Environment Artist, Game Designer, Level Designer, QA, Sound Designer
A21: World Systems | B21: Biome - Farmlands | C21: 4 | D21: 195.4 | E21: Environment Artist
A22: World Systems | B22: Biome - Whispering Woods | C22: 17 | D22: 26.1 | E22: Concept Artist, Environment Artist, Game Designer, Level Designer, QA, Sound Designer
A23: World Systems | B23: Biome - Downtime | C23: 26 | D23: 195.4 | E23: Concept Artist, Environment Artist, Game Designer, Level Designer, QA
A24: Combat
A25: Combat | B25: Combat Framework | C25: 36 | D25: 153 | E25: Animator, Character Artist, Game Designer, Gameplay Developer, QA, VFX Artist
A26: Combat | B26: Ranged Combat | C26: 3 | D26: 9 | E26: Animator, Game Designer
A27: Combat | B27: Enemies Art | C27: 156 | D27: 242 | E27: Animator, Character Artist, Concept Artist, Game Designer, Gameplay Developer, QA, Sound Designer, Technical Artist, VFX Artist
A28: Combat | B28: PvP Combat | C28: 36 | D28: 286.7 | E28: Concept Artist, Environment Artist, Game Designer, Gameplay Developer, Level Designer, QA, Sound Designer, UI/UX Designer
A29: Combat | B29: Combat Balance & Telemetry | C29: 10 | D29: 25 | E29: Backend Developer, Gameplay Developer
A30: Combat | B30: Combat Abilities | C30: 17 | D30: 88 | E30: Animator, Game Designer, Gameplay Developer, QA, Sound Designer, UI/UX Designer
A31: Combat | B31: Magic | C31: 19 | D31: 47 | E31: Animator, Environment Artist, Game Designer, Gameplay Developer, QA, Sound Designer, UI/UX Designer, VFX Artist
A32: Combat | B32: Full Motion Video (FMV) | C32: 45 | D32: 42 | E32: Backend Developer, Concept Artist, Environment Artist, Game Designer, Gameplay Developer, QA, Sound Designer, UI/UX Designer, Writer
A33: User Space
A34: User Space | B34: User Space Server & Instance | C34: 49 | D34: 266.4 | E34: Animator, Backend Developer, Concept Artist, Environment Artist, Game Designer, Gameplay Developer, Level Designer, QA, Sound Designer, UI/UX Designer, VFX Artist
A35: User Space | B35: User Space Decoration | C35: 11 | D35: 51.4 | E35: Concept Artist, Environment Artist, Gameplay Developer
A36: User Space | B36: Building Houses | C36: 3 | D36: 182.9 | E36: Environment Artist
A37: User Space | B37: Anywhere Door Placement | C37: 18 | D37: 34 | E37: Backend Developer, Gameplay Developer, QA
A38: Items & Inventory
A39: Items & Inventory | B39: Item Core System | C39: 30 | D39: 24 | E39: Animator, Character Artist, Concept Artist, Environment Artist, Game Designer, Gameplay Developer, QA, VFX Artist
A40: Items & Inventory | B40: Equipment System | C40: 12 | D40: 30 | E40: Backend Developer, Gameplay Developer
A41: Items & Inventory | B41: Loot Distribution | C41: 19 | D41: 44 | E41: Backend Developer, Game Designer, Gameplay Developer, QA
A42: Items & Inventory | B42: Mounts / Pets | C42: 18 | D42: 12 | E42: Animator, Character Artist, Concept Artist, Game Designer, Gameplay Developer, QA, VFX Artist
A43: Items & Inventory | B43: Consumables | C43: 4 | D43: 1 | E43: Animator, Concept Artist, QA
A44: Player Economy
A45: Player Economy | B45: Trading System | C45: 39 | D45: 77 | E45: Animator, Backend Developer, Character Artist, Concept Artist, Environment Artist, Game Designer, Gameplay Developer, QA, UI/UX Designer
A46: Player Economy | B46: Currency System | C46: 1 | D46: 0 | E46: Concept Artist
A47: Player Economy | B47: Auction House | C47: 2 | D47: 0 | E47: Backend Developer, QA
A48: Player Economy | B48: In-game Store | C48: 27 | D48: 59 | E48: Backend Developer, Game Designer, Gameplay Developer, QA, Sound Designer, UI/UX Designer
A49: Player Economy | B49: In-game Economy | C49: 4 | D49: 5 | E49: Game Designer, QA
A50: Quest System
A51: Quest System | B51: Quests Backend / Tooling | C51: 27 | D51: 36 | E51: Animator, Backend Developer, Character Artist, Concept Artist, Game Designer, Gameplay Developer, QA, UI/UX Designer, Writer
A52: Quest System | B52: Quest Types - Courier / Escort / Kill / Collect / Mystery / Time / Partner / Lockpicking | C52: 29 | D52: 79.5 | E52: Backend Developer, Concept Artist, Game Designer, Gameplay Developer, QA, Sound Designer, Technical Artist, UI/UX Designer, VFX Artist
A53: Quest System | B53: Quest Reward System | C53: 10 | D53: 10 | E53: Concept Artist, Game Designer, Gameplay Developer, QA, Sound Designer, UI/UX Designer
A54: Quest System | B54: Quest Narrative Content | C54: 24 | D54: 99 | E54: Game Designer, Writer
A55: Quest System | B55: In Game Cinematic (IGC) | C55: 24 | D55: 31 | E55: Game Designer, Gameplay Developer, QA, Writer
A56: Social & Multiplayer
A57: Social & Multiplayer | B57: Game Chat System | C57: 35 | D57: 75 | E57: Backend Developer, Gameplay Developer, UI/UX Designer
A58: Social & Multiplayer | B58: Guilds | C58: 30 | D58: 313.3 | E58: Animator, Backend Developer, Character Artist, Concept Artist, Environment Artist, Game Designer, Gameplay Developer, Level Designer, QA, UI/UX Designer
A59: Social & Multiplayer | B59: Co-op / Party | C59: 39 | D59: 72 | E59: Backend Developer, Game Designer, Gameplay Developer, QA, UI/UX Designer
A60: Social & Multiplayer | B60: In-game Mail | C60: 24 | D60: 36 | E60: Backend Developer, Concept Artist, Environment Artist, Gameplay Developer, QA, Sound Designer, UI/UX Designer, VFX Artist
A61: Social & Multiplayer | B61: LFG / Pick-up Groups | C61: 17 | D61: 44 | E61: Backend Developer, Gameplay Developer, UI/UX Designer
A62: Game Bibles
A63: Game Bibles | B63: UX/UI Bible | C63: 1 | D63: 0 | E63: UI/UX Designer
A64: Game Bibles | B64: Brand Bible | C64: 3 | D64: 0 | E64: Concept Artist
A65: Game Bibles | B65: Art Bible | C65: 5 | D65: 0 | E65: Animator, Character Artist, Concept Artist, Environment Artist, VFX Artist
A66: Platform
A67: Platform | B67: Online Services & Backend | C67: 11 | D67: 30 | E67: Backend Developer, Game Designer, Gameplay Developer
A68: Platform | B68: Partner Loop | C68: 33 | D68: 73 | E68: Backend Developer, Game Designer, Gameplay Developer, QA
A69: Live Game
A70: Partner Build
A71: Product Publishing
A72: Product Publishing | B72: Website | C72: 9 | D72: 25 | E72: Backend Developer, Gameplay Developer, UI/UX Designer
